<?xml version="1.0" encoding="UTF-8" standalone="yes" ?>
<!DOCTYPE boost_serialization>
<boost_serialization signature="serialization::archive" version="9">
<tracklets class_id="0" tracking_level="0" version="0">
	<count>1</count>
	<item_version>1</item_version> 
	<item class_id="1" tracking_level="0" version="1">
		<objectType>Car</objectType>
		<h>1.397000</h>
		<w>1.701800</w>
		<l>4.521200</l>
		<first_frame>0</first_frame>
		<poses class_id="2" tracking_level="0" version="0">
			<count>192</count>
			<item_version>2</item_version>
			<item class_id="3" tracking_level="0" version="2">
				<tx>0.519437</tx>
				<ty>3.180400</ty>
				<tz>-0.818297</tz>
				<rx>0.000000</rx>
				<ry>-0.000000</ry>
				<rz>0.000000</rz>
				<state>1</state>
				<occlusion>-1</occlusion>
				<occlusion_kf>-1</occlusion_kf>
				<truncation>-1</truncation>
				<amt_occlusion>0.0</amt_occlusion>
				<amt_occlusion_kf>-1</amt_occlusion_kf>
				<amt_border_l>0.0</amt_border_l>
				<amt_border_r>0.0</amt_border_r>
				<amt_border_kf>-1</amt_border_kf>
			</item>
			<item>
				<tx>0.519477</tx>
				<ty>3.180745</ty>
				<tz>-0.817582</tz>
				<rx>0.000000</rx>
				<ry>-0.000000</ry>
				<rz>0.000000</rz>
				<state>1</state>
				<occlusion>-1</occlusion>
				<occlusion_kf>-1</occlusion_kf>
				<truncation>-1</truncation>
				<amt_occlusion>0.0</amt_occlusion>
				<amt_occlusion_kf>-1</amt_occlusion_kf>
				<amt_border_l>0.0</amt_border_l>
				<amt_border_r>0.0</amt_border_r>
				<amt_border_kf>-1</amt_border_kf>
			</item>
			<item>
				<tx>0.519182</tx>
				<ty>3.181186</ty>
				<tz>-0.816605</tz>
				<rx>0.000000</rx>
				<ry>-0.000000</ry>
				<rz>0.000000</rz>
				<state>1</state>
				<occlusion>-1</occlusion>
				<occlusion_kf>-1</occlusion_kf>
				<truncation>-1</truncation>
				<amt_occlusion>0.0</amt_occlusion>
				<amt_occlusion_kf>-1</amt_occlusion_kf>
				<amt_border_l>0.0</amt_border_l>
				<amt_border_r>0.0</amt_border_r>
				<amt_border_kf>-1</amt_border_kf>
			</item>
			<item>
				<tx>0.518836</tx>
				<ty>3.181649</ty>
				<tz>-0.815626</tz>
				<rx>0.000000</rx>
				<ry>-0.000000</ry>
				<rz>0.000000</rz>
				<state>1</state>
				<occlusion>-1</occlusion>
				<occlusion_kf>-1</occlusion_kf>
				<truncation>-1</truncation>
				<amt_occlusion>0.0</amt_occlusion>
				<amt_occlusion_kf>-1</amt_occlusion_kf>
				<amt_border_l>0.0</amt_border_l>
				<amt_border_r>0.0</amt_border_r>
				<amt_border_kf>-1</amt_border_kf>
			</item>
			<item>
				<tx>0.509085</tx>
				<ty>3.181544</ty>
				<tz>-0.816542</tz>
				<rx>0.000000</rx>
				<ry>-0.000000</ry>
				<rz>0.000000</rz>
				<state>1</state>
				<occlusion>-1</occlusion>
				<occlusion_kf>-1</occlusion_kf>
				<truncation>-1</truncation>
				<amt_occlusion>0.0</amt_occlusion>
				<amt_occlusion_kf>-1</amt_occlusion_kf>
				<amt_border_l>0.0</amt_border_l>
				<amt_border_r>0.0</amt_border_r>
				<amt_border_kf>-1</amt_border_kf>
			</item>
			<item>
				<tx>0.498478</tx>
				<ty>3.180462</ty>
				<tz>-0.820142</tz>
				<rx>0.000000</rx>
				<ry>-0.000000</ry>
				<rz>0.000000</rz>
				<state>1</state>
				<occlusion>-1</occlusion>
				<occlusion_kf>-1</occlusion_kf>
				<truncation>-1</truncation>
				<amt_occlusion>0.0</amt_occlusion>
				<amt_occlusion_kf>-1</amt_occlusion_kf>
				<amt_border_l>0.0</amt_border_l>
				<amt_border_r>0.0</amt_border_r>
				<amt_border_kf>-1</amt_border_kf>
			</item>
			<item>
				<tx>0.487175</tx>
				<ty>3.181030</ty>
				<tz>-0.821399</tz>
				<rx>0.000000</rx>
				<ry>-0.000000</ry>
				<rz>0.000000</rz>
				<state>1</state>
				<occlusion>-1</occlusion>
				<occlusion_kf>-1</occlusion_kf>
				<truncation>-1</truncation>
				<amt_occlusion>0.0</amt_occlusion>
				<amt_occlusion_kf>-1</amt_occlusion_kf>
				<amt_border_l>0.0</amt_border_l>
				<amt_border_r>0.0</amt_border_r>
				<amt_border_kf>-1</amt_border_kf>
			</item>
			<item>
				<tx>0.475031</tx>
				<ty>3.182343</ty>
				<tz>-0.821817</tz>
				<rx>0.000000</rx>
				<ry>-0.000000</ry>
				<rz>0.000000</rz>
				<state>1</state>
				<occlusion>-1</occlusion>
				<occlusion_kf>-1</occlusion_kf>
				<truncation>-1</truncation>
				<amt_occlusion>0.0</amt_occlusion>
				<amt_occlusion_kf>-1</amt_occlusion_kf>
				<amt_border_l>0.0</amt_border_l>
				<amt_border_r>0.0</amt_border_r>
				<amt_border_kf>-1</amt_border_kf>
			</item>
			<item>
				<tx>0.462732</tx>
				<ty>3.183271</ty>
				<tz>-0.822100</tz>
				<rx>0.000000</rx>
				<ry>-0.000000</ry>
				<rz>0.000000</rz>
				<state>1</state>
				<occlusion>-1</occlusion>
				<occlusion_kf>-1</occlusion_kf>
				<truncation>-1</truncation>
				<amt_occlusion>0.0</amt_occlusion>
				<amt_occlusion_kf>-1</amt_occlusion_kf>
				<amt_border_l>0.0</amt_border_l>
				<amt_border_r>0.0</amt_border_r>
				<amt_border_kf>-1</amt_border_kf>
			</item>
			<item>
				<tx>0.444615</tx>
				<ty>3.182498</ty>
				<tz>-0.822100</tz>
				<rx>0.000000</rx>
				<ry>-0.000000</ry>
				<rz>0.000000</rz>
				<state>1</state>
				<occlusion>-1</occlusion>
				<occlusion_kf>-1</occlusion_kf>
				<truncation>-1</truncation>
				<amt_occlusion>0.0</amt_occlusion>
				<amt_occlusion_kf>-1</amt_occlusion_kf>
				<amt_border_l>0.0</amt_border_l>
				<amt_border_r>0.0</amt_border_r>
				<amt_border_kf>-1</amt_border_kf>
			</item>
			<item>
				<tx>0.421589</tx>
				<ty>3.181097</ty>
				<tz>-0.822100</tz>
				<rx>0.000000</rx>
				<ry>-0.000000</ry>
				<rz>0.000000</rz>
				<state>1</state>
				<occlusion>-1</occlusion>
				<occlusion_kf>-1</occlusion_kf>
				<truncation>-1</truncation>
				<amt_occlusion>0.0</amt_occlusion>
				<amt_occlusion_kf>-1</amt_occlusion_kf>
				<amt_border_l>0.0</amt_border_l>
				<amt_border_r>0.0</amt_border_r>
				<amt_border_kf>-1</amt_border_kf>
			</item>
			<item>
				<tx>0.391527</tx>
				<ty>3.182374</ty>
				<tz>-0.820277</tz>
				<rx>0.000000</rx>
				<ry>-0.000000</ry>
				<rz>0.000000</rz>
				<state>1</state>
				<occlusion>-1</occlusion>
				<occlusion_kf>-1</occlusion_kf>
				<truncation>-1</truncation>
				<amt_occlusion>0.0</amt_occlusion>
				<amt_occlusion_kf>-1</amt_occlusion_kf>
				<amt_border_l>0.0</amt_border_l>
				<amt_border_r>0.0</amt_border_r>
				<amt_border_kf>-1</amt_border_kf>
			</item>
			<item>
				<tx>0.360397</tx>
				<ty>3.183761</ty>
				<tz>-0.818177</tz>
				<rx>0.000000</rx>
				<ry>-0.000000</ry>
				<rz>0.000000</rz>
				<state>1</state>
				<occlusion>-1</occlusion>
				<occlusion_kf>-1</occlusion_kf>
				<truncation>-1</truncation>
				<amt_occlusion>0.0</amt_occlusion>
				<amt_occlusion_kf>-1</amt_occlusion_kf>
				<amt_border_l>0.0</amt_border_l>
				<amt_border_r>0.0</amt_border_r>
				<amt_border_kf>-1</amt_border_kf>
			</item>
			<item>
				<tx>0.324507</tx>
				<ty>3.186037</ty>
				<tz>-0.816192</tz>
				<rx>0.000000</rx>
				<ry>-0.000000</ry>
				<rz>0.000000</rz>
				<state>1</state>
				<occlusion>-1</occlusion>
				<occlusion_kf>-1</occlusion_kf>
				<truncation>-1</truncation>
				<amt_occlusion>0.0</amt_occlusion>
				<amt_occlusion_kf>-1</amt_occlusion_kf>
				<amt_border_l>0.0</amt_border_l>
				<amt_border_r>0.0</amt_border_r>
				<amt_border_kf>-1</amt_border_kf>
			</item>
			<item>
				<tx>0.282676</tx>
				<ty>3.189455</ty>
				<tz>-0.814110</tz>
				<rx>0.000000</rx>
				<ry>-0.000000</ry>
				<rz>0.000000</rz>
				<state>1</state>
				<occlusion>-1</occlusion>
				<occlusion_kf>-1</occlusion_kf>
				<truncation>-1</truncation>
				<amt_occlusion>0.0</amt_occlusion>
				<amt_occlusion_kf>-1</amt_occlusion_kf>
				<amt_border_l>0.0</amt_border_l>
				<amt_border_r>0.0</amt_border_r>
				<amt_border_kf>-1</amt_border_kf>
			</item>
			<item>
				<tx>0.240227</tx>
				<ty>3.192869</ty>
				<tz>-0.811982</tz>
				<rx>0.000000</rx>
				<ry>-0.000000</ry>
				<rz>0.000000</rz>
				<state>1</state>
				<occlusion>-1</occlusion>
				<occlusion_kf>-1</occlusion_kf>
				<truncation>-1</truncation>
				<amt_occlusion>0.0</amt_occlusion>
				<amt_occlusion_kf>-1</amt_occlusion_kf>
				<amt_border_l>0.0</amt_border_l>
				<amt_border_r>0.0</amt_border_r>
				<amt_border_kf>-1</amt_border_kf>
			</item>
			<item>
				<tx>0.183310</tx>
				<ty>3.199446</ty>
				<tz>-0.810746</tz>
				<rx>0.000000</rx>
				<ry>-0.000000</ry>
				<rz>0.000000</rz>
				<state>1</state>
				<occlusion>-1</occlusion>
				<occlusion_kf>-1</occlusion_kf>
				<truncation>-1</truncation>
				<amt_occlusion>0.0</amt_occlusion>
				<amt_occlusion_kf>-1</amt_occlusion_kf>
				<amt_border_l>0.0</amt_border_l>
				<amt_border_r>0.0</amt_border_r>
				<amt_border_kf>-1</amt_border_kf>
			</item>
			<item>
				<tx>0.126330</tx>
				<ty>3.205548</ty>
				<tz>-0.809509</tz>
				<rx>0.000000</rx>
				<ry>-0.000000</ry>
				<rz>0.000000</rz>
				<state>1</state>
				<occlusion>-1</occlusion>
				<occlusion_kf>-1</occlusion_kf>
				<truncation>-1</truncation>
				<amt_occlusion>0.0</amt_occlusion>
				<amt_occlusion_kf>-1</amt_occlusion_kf>
				<amt_border_l>0.0</amt_border_l>
				<amt_border_r>0.0</amt_border_r>
				<amt_border_kf>-1</amt_border_kf>
			</item>
			<item>
				<tx>0.062011</tx>
				<ty>3.212598</ty>
				<tz>-0.809443</tz>
				<rx>0.000000</rx>
				<ry>-0.000000</ry>
				<rz>0.000000</rz>
				<state>1</state>
				<occlusion>-1</occlusion>
				<occlusion_kf>-1</occlusion_kf>
				<truncation>-1</truncation>
				<amt_occlusion>0.0</amt_occlusion>
				<amt_occlusion_kf>-1</amt_occlusion_kf>
				<amt_border_l>0.0</amt_border_l>
				<amt_border_r>0.0</amt_border_r>
				<amt_border_kf>-1</amt_border_kf>
			</item>
			<item>
				<tx>-0.007669</tx>
				<ty>3.220109</ty>
				<tz>-0.809859</tz>
				<rx>0.000000</rx>
				<ry>-0.000000</ry>
				<rz>0.000000</rz>
				<state>1</state>
				<occlusion>-1</occlusion>
				<occlusion_kf>-1</occlusion_kf>
				<truncation>-1</truncation>
				<amt_occlusion>0.0</amt_occlusion>
				<amt_occlusion_kf>-1</amt_occlusion_kf>
				<amt_border_l>0.0</amt_border_l>
				<amt_border_r>0.0</amt_border_r>
				<amt_border_kf>-1</amt_border_kf>
			</item>
			<item>
				<tx>-0.080355</tx>
				<ty>3.227314</ty>
				<tz>-0.809877</tz>
				<rx>0.000000</rx>
				<ry>-0.000000</ry>
				<rz>0.000000</rz>
				<state>1</state>
				<occlusion>-1</occlusion>
				<occlusion_kf>-1</occlusion_kf>
				<truncation>-1</truncation>
				<amt_occlusion>0.0</amt_occlusion>
				<amt_occlusion_kf>-1</amt_occlusion_kf>
				<amt_border_l>0.0</amt_border_l>
				<amt_border_r>0.0</amt_border_r>
				<amt_border_kf>-1</amt_border_kf>
			</item>
			<item>
				<tx>-0.164946</tx>
				<ty>3.235272</ty>
				<tz>-0.809457</tz>
				<rx>0.000000</rx>
				<ry>-0.000000</ry>
				<rz>0.000000</rz>
				<state>1</state>
				<occlusion>-1</occlusion>
				<occlusion_kf>-1</occlusion_kf>
				<truncation>-1</truncation>
				<amt_occlusion>0.0</amt_occlusion>
				<amt_occlusion_kf>-1</amt_occlusion_kf>
				<amt_border_l>0.0</amt_border_l>
				<amt_border_r>0.0</amt_border_r>
				<amt_border_kf>-1</amt_border_kf>
			</item>
			<item>
				<tx>-0.249610</tx>
				<ty>3.242134</ty>
				<tz>-0.809037</tz>
				<rx>0.000000</rx>
				<ry>-0.000000</ry>
				<rz>0.000000</rz>
				<state>1</state>
				<occlusion>-1</occlusion>
				<occlusion_kf>-1</occlusion_kf>
				<truncation>-1</truncation>
				<amt_occlusion>0.0</amt_occlusion>
				<amt_occlusion_kf>-1</amt_occlusion_kf>
				<amt_border_l>0.0</amt_border_l>
				<amt_border_r>0.0</amt_border_r>
				<amt_border_kf>-1</amt_border_kf>
			</item>
			<item>
				<tx>-0.345421</tx>
				<ty>3.248384</ty>
				<tz>-0.808343</tz>
				<rx>0.000000</rx>
				<ry>-0.000000</ry>
				<rz>0.000000</rz>
				<state>1</state>
				<occlusion>-1</occlusion>
				<occlusion_kf>-1</occlusion_kf>
				<truncation>-1</truncation>
				<amt_occlusion>0.0</amt_occlusion>
				<amt_occlusion_kf>-1</amt_occlusion_kf>
				<amt_border_l>0.0</amt_border_l>
				<amt_border_r>0.0</amt_border_r>
				<amt_border_kf>-1</amt_border_kf>
			</item>
			<item>
				<tx>-0.443599</tx>
				<ty>3.253240</ty>
				<tz>-0.807516</tz>
				<rx>0.000000</rx>
				<ry>-0.000000</ry>
				<rz>0.000000</rz>
				<state>1</state>
				<occlusion>-1</occlusion>
				<occlusion_kf>-1</occlusion_kf>
				<truncation>-1</truncation>
				<amt_occlusion>0.0</amt_occlusion>
				<amt_occlusion_kf>-1</amt_occlusion_kf>
				<amt_border_l>0.0</amt_border_l>
				<amt_border_r>0.0</amt_border_r>
				<amt_border_kf>-1</amt_border_kf>
			</item>
			<item>
				<tx>-0.545968</tx>
				<ty>3.258126</ty>
				<tz>-0.806467</tz>
				<rx>0.000000</rx>
				<ry>-0.000000</ry>
				<rz>0.000000</rz>
				<state>1</state>
				<occlusion>-1</occlusion>
				<occlusion_kf>-1</occlusion_kf>
				<truncation>-1</truncation>
				<amt_occlusion>0.0</amt_occlusion>
				<amt_occlusion_kf>-1</amt_occlusion_kf>
				<amt_border_l>0.0</amt_border_l>
				<amt_border_r>0.0</amt_border_r>
				<amt_border_kf>-1</amt_border_kf>
			</item>
			<item>
				<tx>-0.658353</tx>
				<ty>3.264204</ty>
				<tz>-0.804962</tz>
				<rx>0.000000</rx>
				<ry>-0.000000</ry>
				<rz>0.000000</rz>
				<state>1</state>
				<occlusion>-1</occlusion>
				<occlusion_kf>-1</occlusion_kf>
				<truncation>-1</truncation>
				<amt_occlusion>0.0</amt_occlusion>
				<amt_occlusion_kf>-1</amt_occlusion_kf>
				<amt_border_l>0.0</amt_border_l>
				<amt_border_r>0.0</amt_border_r>
				<amt_border_kf>-1</amt_border_kf>
			</item>
			<item>
				<tx>-0.771171</tx>
				<ty>3.268477</ty>
				<tz>-0.803444</tz>
				<rx>0.000000</rx>
				<ry>-0.000000</ry>
				<rz>0.000000</rz>
				<state>1</state>
				<occlusion>-1</occlusion>
				<occlusion_kf>-1</occlusion_kf>
				<truncation>-1</truncation>
				<amt_occlusion>0.0</amt_occlusion>
				<amt_occlusion_kf>-1</amt_occlusion_kf>
				<amt_border_l>0.0</amt_border_l>
				<amt_border_r>0.0</amt_border_r>
				<amt_border_kf>-1</amt_border_kf>
			</item>
			<item>
				<tx>-0.893817</tx>
				<ty>3.273703</ty>
				<tz>-0.803425</tz>
				<rx>0.000000</rx>
				<ry>-0.000000</ry>
				<rz>0.000000</rz>
				<state>1</state>
				<occlusion>-1</occlusion>
				<occlusion_kf>-1</occlusion_kf>
				<truncation>-1</truncation>
				<amt_occlusion>0.0</amt_occlusion>
				<amt_occlusion_kf>-1</amt_occlusion_kf>
				<amt_border_l>0.0</amt_border_l>
				<amt_border_r>0.0</amt_border_r>
				<amt_border_kf>-1</amt_border_kf>
			</item>
			<item>
				<tx>-1.016870</tx>
				<ty>3.276951</ty>
				<tz>-0.807522</tz>
				<rx>0.000000</rx>
				<ry>-0.000000</ry>
				<rz>0.000000</rz>
				<state>1</state>
				<occlusion>-1</occlusion>
				<occlusion_kf>-1</occlusion_kf>
				<truncation>-1</truncation>
				<amt_occlusion>0.0</amt_occlusion>
				<amt_occlusion_kf>-1</amt_occlusion_kf>
				<amt_border_l>0.0</amt_border_l>
				<amt_border_r>0.0</amt_border_r>
				<amt_border_kf>-1</amt_border_kf>
			</item>
			<item>
				<tx>-1.130961</tx>
				<ty>3.278502</ty>
				<tz>-0.807602</tz>
				<rx>0.000000</rx>
				<ry>-0.000000</ry>
				<rz>0.000000</rz>
				<state>1</state>
				<occlusion>-1</occlusion>
				<occlusion_kf>-1</occlusion_kf>
				<truncation>-1</truncation>
				<amt_occlusion>0.0</amt_occlusion>
				<amt_occlusion_kf>-1</amt_occlusion_kf>
				<amt_border_l>0.0</amt_border_l>
				<amt_border_r>0.0</amt_border_r>
				<amt_border_kf>-1</amt_border_kf>
			</item>
			<item>
				<tx>-1.239723</tx>
				<ty>3.278807</ty>
				<tz>-0.806858</tz>
				<rx>0.000000</rx>
				<ry>-0.000000</ry>
				<rz>0.000000</rz>
				<state>1</state>
				<occlusion>-1</occlusion>
				<occlusion_kf>-1</occlusion_kf>
				<truncation>-1</truncation>
				<amt_occlusion>0.0</amt_occlusion>
				<amt_occlusion_kf>-1</amt_occlusion_kf>
				<amt_border_l>0.0</amt_border_l>
				<amt_border_r>0.0</amt_border_r>
				<amt_border_kf>-1</amt_border_kf>
			</item>
			<item>
				<tx>-1.347861</tx>
				<ty>3.277605</ty>
				<tz>-0.806253</tz>
				<rx>0.000000</rx>
				<ry>-0.000000</ry>
				<rz>0.000000</rz>
				<state>1</state>
				<occlusion>-1</occlusion>
				<occlusion_kf>-1</occlusion_kf>
				<truncation>-1</truncation>
				<amt_occlusion>0.0</amt_occlusion>
				<amt_occlusion_kf>-1</amt_occlusion_kf>
				<amt_border_l>0.0</amt_border_l>
				<amt_border_r>0.0</amt_border_r>
				<amt_border_kf>-1</amt_border_kf>
			</item>
			<item>
				<tx>-1.506898</tx>
				<ty>3.275532</ty>
				<tz>-0.803950</tz>
				<rx>0.000000</rx>
				<ry>-0.000000</ry>
				<rz>0.000000</rz>
				<state>1</state>
				<occlusion>-1</occlusion>
				<occlusion_kf>-1</occlusion_kf>
				<truncation>-1</truncation>
				<amt_occlusion>0.0</amt_occlusion>
				<amt_occlusion_kf>-1</amt_occlusion_kf>
				<amt_border_l>0.0</amt_border_l>
				<amt_border_r>0.0</amt_border_r>
				<amt_border_kf>-1</amt_border_kf>
			</item>
			<item>
				<tx>-1.708518</tx>
				<ty>3.269335</ty>
				<tz>-0.799953</tz>
				<rx>0.000000</rx>
				<ry>-0.000000</ry>
				<rz>0.000000</rz>
				<state>1</state>
				<occlusion>-1</occlusion>
				<occlusion_kf>-1</occlusion_kf>
				<truncation>-1</truncation>
				<amt_occlusion>0.0</amt_occlusion>
				<amt_occlusion_kf>-1</amt_occlusion_kf>
				<amt_border_l>0.0</amt_border_l>
				<amt_border_r>0.0</amt_border_r>
				<amt_border_kf>-1</amt_border_kf>
			</item>
			<item>
				<tx>-1.877662</tx>
				<ty>3.261658</ty>
				<tz>-0.796415</tz>
				<rx>0.000000</rx>
				<ry>-0.000000</ry>
				<rz>0.000000</rz>
				<state>1</state>
				<occlusion>-1</occlusion>
				<occlusion_kf>-1</occlusion_kf>
				<truncation>-1</truncation>
				<amt_occlusion>0.0</amt_occlusion>
				<amt_occlusion_kf>-1</amt_occlusion_kf>
				<amt_border_l>0.0</amt_border_l>
				<amt_border_r>0.0</amt_border_r>
				<amt_border_kf>-1</amt_border_kf>
			</item>
			<item>
				<tx>-2.038640</tx>
				<ty>3.251031</ty>
				<tz>-0.793079</tz>
				<rx>0.000000</rx>
				<ry>-0.000000</ry>
				<rz>0.000000</rz>
				<state>1</state>
				<occlusion>-1</occlusion>
				<occlusion_kf>-1</occlusion_kf>
				<truncation>-1</truncation>
				<amt_occlusion>0.0</amt_occlusion>
				<amt_occlusion_kf>-1</amt_occlusion_kf>
				<amt_border_l>0.0</amt_border_l>
				<amt_border_r>0.0</amt_border_r>
				<amt_border_kf>-1</amt_border_kf>
			</item>
			<item>
				<tx>-2.202260</tx>
				<ty>3.239005</ty>
				<tz>-0.790775</tz>
				<rx>0.000000</rx>
				<ry>-0.000000</ry>
				<rz>0.000000</rz>
				<state>1</state>
				<occlusion>-1</occlusion>
				<occlusion_kf>-1</occlusion_kf>
				<truncation>-1</truncation>
				<amt_occlusion>0.0</amt_occlusion>
				<amt_occlusion_kf>-1</amt_occlusion_kf>
				<amt_border_l>0.0</amt_border_l>
				<amt_border_r>0.0</amt_border_r>
				<amt_border_kf>-1</amt_border_kf>
			</item>
			<item>
				<tx>-2.372019</tx>
				<ty>3.226094</ty>
				<tz>-0.789942</tz>
				<rx>0.000000</rx>
				<ry>-0.000000</ry>
				<rz>0.000000</rz>
				<state>1</state>
				<occlusion>-1</occlusion>
				<occlusion_kf>-1</occlusion_kf>
				<truncation>-1</truncation>
				<amt_occlusion>0.0</amt_occlusion>
				<amt_occlusion_kf>-1</amt_occlusion_kf>
				<amt_border_l>0.0</amt_border_l>
				<amt_border_r>0.0</amt_border_r>
				<amt_border_kf>-1</amt_border_kf>
			</item>
			<item>
				<tx>-2.541556</tx>
				<ty>3.209571</ty>
				<tz>-0.788996</tz>
				<rx>0.000000</rx>
				<ry>-0.000000</ry>
				<rz>0.000000</rz>
				<state>1</state>
				<occlusion>-1</occlusion>
				<occlusion_kf>-1</occlusion_kf>
				<truncation>-1</truncation>
				<amt_occlusion>0.0</amt_occlusion>
				<amt_occlusion_kf>-1</amt_occlusion_kf>
				<amt_border_l>0.0</amt_border_l>
				<amt_border_r>0.0</amt_border_r>
				<amt_border_kf>-1</amt_border_kf>
			</item>
			<item>
				<tx>-2.724750</tx>
				<ty>3.189616</ty>
				<tz>-0.788979</tz>
				<rx>0.000000</rx>
				<ry>-0.000000</ry>
				<rz>0.000000</rz>
				<state>1</state>
				<occlusion>-1</occlusion>
				<occlusion_kf>-1</occlusion_kf>
				<truncation>-1</truncation>
				<amt_occlusion>0.0</amt_occlusion>
				<amt_occlusion_kf>-1</amt_occlusion_kf>
				<amt_border_l>0.0</amt_border_l>
				<amt_border_r>0.0</amt_border_r>
				<amt_border_kf>-1</amt_border_kf>
			</item>
			<item>
				<tx>-2.908146</tx>
				<ty>3.165034</ty>
				<tz>-0.788979</tz>
				<rx>0.000000</rx>
				<ry>-0.000000</ry>
				<rz>0.000000</rz>
				<state>1</state>
				<occlusion>-1</occlusion>
				<occlusion_kf>-1</occlusion_kf>
				<truncation>-1</truncation>
				<amt_occlusion>0.0</amt_occlusion>
				<amt_occlusion_kf>-1</amt_occlusion_kf>
				<amt_border_l>0.0</amt_border_l>
				<amt_border_r>0.0</amt_border_r>
				<amt_border_kf>-1</amt_border_kf>
			</item>
			<item>
				<tx>-3.091628</tx>
				<ty>3.143149</ty>
				<tz>-0.789754</tz>
				<rx>0.000000</rx>
				<ry>-0.000000</ry>
				<rz>0.000000</rz>
				<state>1</state>
				<occlusion>-1</occlusion>
				<occlusion_kf>-1</occlusion_kf>
				<truncation>-1</truncation>
				<amt_occlusion>0.0</amt_occlusion>
				<amt_occlusion_kf>-1</amt_occlusion_kf>
				<amt_border_l>0.0</amt_border_l>
				<amt_border_r>0.0</amt_border_r>
				<amt_border_kf>-1</amt_border_kf>
			</item>
			<item>
				<tx>-3.287001</tx>
				<ty>3.119287</ty>
				<tz>-0.791071</tz>
				<rx>0.000000</rx>
				<ry>-0.000000</ry>
				<rz>0.000000</rz>
				<state>1</state>
				<occlusion>-1</occlusion>
				<occlusion_kf>-1</occlusion_kf>
				<truncation>-1</truncation>
				<amt_occlusion>0.0</amt_occlusion>
				<amt_occlusion_kf>-1</amt_occlusion_kf>
				<amt_border_l>0.0</amt_border_l>
				<amt_border_r>0.0</amt_border_r>
				<amt_border_kf>-1</amt_border_kf>
			</item>
			<item>
				<tx>-3.459014</tx>
				<ty>3.096809</ty>
				<tz>-0.791366</tz>
				<rx>0.000000</rx>
				<ry>-0.000000</ry>
				<rz>0.000000</rz>
				<state>1</state>
				<occlusion>-1</occlusion>
				<occlusion_kf>-1</occlusion_kf>
				<truncation>-1</truncation>
				<amt_occlusion>0.0</amt_occlusion>
				<amt_occlusion_kf>-1</amt_occlusion_kf>
				<amt_border_l>0.0</amt_border_l>
				<amt_border_r>0.0</amt_border_r>
				<amt_border_kf>-1</amt_border_kf>
			</item>
			<item>
				<tx>-3.635713</tx>
				<ty>3.077359</ty>
				<tz>-0.789637</tz>
				<rx>0.000000</rx>
				<ry>-0.000000</ry>
				<rz>0.000000</rz>
				<state>1</state>
				<occlusion>-1</occlusion>
				<occlusion_kf>-1</occlusion_kf>
				<truncation>-1</truncation>
				<amt_occlusion>0.0</amt_occlusion>
				<amt_occlusion_kf>-1</amt_occlusion_kf>
				<amt_border_l>0.0</amt_border_l>
				<amt_border_r>0.0</amt_border_r>
				<amt_border_kf>-1</amt_border_kf>
			</item>
			<item>
				<tx>-3.812340</tx>
				<ty>3.054506</ty>
				<tz>-0.787910</tz>
				<rx>0.000000</rx>
				<ry>-0.000000</ry>
				<rz>0.000000</rz>
				<state>1</state>
				<occlusion>-1</occlusion>
				<occlusion_kf>-1</occlusion_kf>
				<truncation>-1</truncation>
				<amt_occlusion>0.0</amt_occlusion>
				<amt_occlusion_kf>-1</amt_occlusion_kf>
				<amt_border_l>0.0</amt_border_l>
				<amt_border_r>0.0</amt_border_r>
				<amt_border_kf>-1</amt_border_kf>
			</item>
			<item>
				<tx>-4.004427</tx>
				<ty>3.030828</ty>
				<tz>-0.788668</tz>
				<rx>0.000000</rx>
				<ry>-0.000000</ry>
				<rz>0.000000</rz>
				<state>1</state>
				<occlusion>-1</occlusion>
				<occlusion_kf>-1</occlusion_kf>
				<truncation>-1</truncation>
				<amt_occlusion>0.0</amt_occlusion>
				<amt_occlusion_kf>-1</amt_occlusion_kf>
				<amt_border_l>0.0</amt_border_l>
				<amt_border_r>0.0</amt_border_r>
				<amt_border_kf>-1</amt_border_kf>
			</item>
			<item>
				<tx>-4.216736</tx>
				<ty>3.001423</ty>
				<tz>-0.789586</tz>
				<rx>0.000000</rx>
				<ry>-0.000000</ry>
				<rz>0.000000</rz>
				<state>1</state>
				<occlusion>-1</occlusion>
				<occlusion_kf>-1</occlusion_kf>
				<truncation>-1</truncation>
				<amt_occlusion>0.0</amt_occlusion>
				<amt_occlusion_kf>-1</amt_occlusion_kf>
				<amt_border_l>0.0</amt_border_l>
				<amt_border_r>0.0</amt_border_r>
				<amt_border_kf>-1</amt_border_kf>
			</item>
			<item>
				<tx>-4.403880</tx>
				<ty>2.976308</ty>
				<tz>-0.789542</tz>
				<rx>0.000000</rx>
				<ry>-0.000000</ry>
				<rz>0.000000</rz>
				<state>1</state>
				<occlusion>-1</occlusion>
				<occlusion_kf>-1</occlusion_kf>
				<truncation>-1</truncation>
				<amt_occlusion>0.0</amt_occlusion>
				<amt_occlusion_kf>-1</amt_occlusion_kf>
				<amt_border_l>0.0</amt_border_l>
				<amt_border_r>0.0</amt_border_r>
				<amt_border_kf>-1</amt_border_kf>
			</item>
			<item>
				<tx>-4.600989</tx>
				<ty>2.950861</ty>
				<tz>-0.787673</tz>
				<rx>0.000000</rx>
				<ry>-0.000000</ry>
				<rz>0.000000</rz>
				<state>1</state>
				<occlusion>-1</occlusion>
				<occlusion_kf>-1</occlusion_kf>
				<truncation>-1</truncation>
				<amt_occlusion>0.0</amt_occlusion>
				<amt_occlusion_kf>-1</amt_occlusion_kf>
				<amt_border_l>0.0</amt_border_l>
				<amt_border_r>0.0</amt_border_r>
				<amt_border_kf>-1</amt_border_kf>
			</item>
			<item>
				<tx>-4.797416</tx>
				<ty>2.922739</ty>
				<tz>-0.785806</tz>
				<rx>0.000000</rx>
				<ry>-0.000000</ry>
				<rz>0.000000</rz>
				<state>1</state>
				<occlusion>-1</occlusion>
				<occlusion_kf>-1</occlusion_kf>
				<truncation>-1</truncation>
				<amt_occlusion>0.0</amt_occlusion>
				<amt_occlusion_kf>-1</amt_occlusion_kf>
				<amt_border_l>0.0</amt_border_l>
				<amt_border_r>0.0</amt_border_r>
				<amt_border_kf>-1</amt_border_kf>
			</item>
			<item>
				<tx>-4.999694</tx>
				<ty>2.894698</ty>
				<tz>-0.788127</tz>
				<rx>0.000000</rx>
				<ry>-0.000000</ry>
				<rz>0.000000</rz>
				<state>1</state>
				<occlusion>-1</occlusion>
				<occlusion_kf>-1</occlusion_kf>
				<truncation>-1</truncation>
				<amt_occlusion>0.0</amt_occlusion>
				<amt_occlusion_kf>-1</amt_occlusion_kf>
				<amt_border_l>0.0</amt_border_l>
				<amt_border_r>0.0</amt_border_r>
				<amt_border_kf>-1</amt_border_kf>
			</item>
			<item>
				<tx>-5.214560</tx>
				<ty>2.861104</ty>
				<tz>-0.793189</tz>
				<rx>0.000000</rx>
				<ry>-0.000000</ry>
				<rz>0.000000</rz>
				<state>1</state>
				<occlusion>-1</occlusion>
				<occlusion_kf>-1</occlusion_kf>
				<truncation>-1</truncation>
				<amt_occlusion>0.0</amt_occlusion>
				<amt_occlusion_kf>-1</amt_occlusion_kf>
				<amt_border_l>0.0</amt_border_l>
				<amt_border_r>0.0</amt_border_r>
				<amt_border_kf>-1</amt_border_kf>
			</item>
			<item>
				<tx>-5.380326</tx>
				<ty>2.836564</ty>
				<tz>-0.792719</tz>
				<rx>0.000000</rx>
				<ry>-0.000000</ry>
				<rz>0.000000</rz>
				<state>1</state>
				<occlusion>-1</occlusion>
				<occlusion_kf>-1</occlusion_kf>
				<truncation>-1</truncation>
				<amt_occlusion>0.0</amt_occlusion>
				<amt_occlusion_kf>-1</amt_occlusion_kf>
				<amt_border_l>0.0</amt_border_l>
				<amt_border_r>0.0</amt_border_r>
				<amt_border_kf>-1</amt_border_kf>
			</item>
			<item>
				<tx>-5.540020</tx>
				<ty>2.812440</ty>
				<tz>-0.790583</tz>
				<rx>0.000000</rx>
				<ry>-0.000000</ry>
				<rz>0.000000</rz>
				<state>1</state>
				<occlusion>-1</occlusion>
				<occlusion_kf>-1</occlusion_kf>
				<truncation>-1</truncation>
				<amt_occlusion>0.0</amt_occlusion>
				<amt_occlusion_kf>-1</amt_occlusion_kf>
				<amt_border_l>0.0</amt_border_l>
				<amt_border_r>0.0</amt_border_r>
				<amt_border_kf>-1</amt_border_kf>
			</item>
			<item>
				<tx>-5.698998</tx>
				<ty>2.786620</ty>
				<tz>-0.788878</tz>
				<rx>0.000000</rx>
				<ry>-0.000000</ry>
				<rz>0.000000</rz>
				<state>1</state>
				<occlusion>-1</occlusion>
				<occlusion_kf>-1</occlusion_kf>
				<truncation>-1</truncation>
				<amt_occlusion>0.0</amt_occlusion>
				<amt_occlusion_kf>-1</amt_occlusion_kf>
				<amt_border_l>0.0</amt_border_l>
				<amt_border_r>0.0</amt_border_r>
				<amt_border_kf>-1</amt_border_kf>
			</item>
			<item>
				<tx>-5.921858</tx>
				<ty>2.756562</ty>
				<tz>-0.786901</tz>
				<rx>0.000000</rx>
				<ry>-0.000000</ry>
				<rz>0.000000</rz>
				<state>1</state>
				<occlusion>-1</occlusion>
				<occlusion_kf>-1</occlusion_kf>
				<truncation>-1</truncation>
				<amt_occlusion>0.0</amt_occlusion>
				<amt_occlusion_kf>-1</amt_occlusion_kf>
				<amt_border_l>0.0</amt_border_l>
				<amt_border_r>0.0</amt_border_r>
				<amt_border_kf>-1</amt_border_kf>
			</item>
			<item>
				<tx>-6.220372</tx>
				<ty>2.718862</ty>
				<tz>-0.783719</tz>
				<rx>0.000000</rx>
				<ry>-0.000000</ry>
				<rz>0.000000</rz>
				<state>1</state>
				<occlusion>-1</occlusion>
				<occlusion_kf>-1</occlusion_kf>
				<truncation>-1</truncation>
				<amt_occlusion>0.0</amt_occlusion>
				<amt_occlusion_kf>-1</amt_occlusion_kf>
				<amt_border_l>0.0</amt_border_l>
				<amt_border_r>0.0</amt_border_r>
				<amt_border_kf>-1</amt_border_kf>
			</item>
			<item>
				<tx>-6.436796</tx>
				<ty>2.691356</ty>
				<tz>-0.784623</tz>
				<rx>0.000000</rx>
				<ry>-0.000000</ry>
				<rz>0.000000</rz>
				<state>1</state>
				<occlusion>-1</occlusion>
				<occlusion_kf>-1</occlusion_kf>
				<truncation>-1</truncation>
				<amt_occlusion>0.0</amt_occlusion>
				<amt_occlusion_kf>-1</amt_occlusion_kf>
				<amt_border_l>0.0</amt_border_l>
				<amt_border_r>0.0</amt_border_r>
				<amt_border_kf>-1</amt_border_kf>
			</item>
			<item>
				<tx>-6.654871</tx>
				<ty>2.658380</ty>
				<tz>-0.786714</tz>
				<rx>0.000000</rx>
				<ry>-0.000000</ry>
				<rz>0.000000</rz>
				<state>1</state>
				<occlusion>-1</occlusion>
				<occlusion_kf>-1</occlusion_kf>
				<truncation>-1</truncation>
				<amt_occlusion>0.0</amt_occlusion>
				<amt_occlusion_kf>-1</amt_occlusion_kf>
				<amt_border_l>0.0</amt_border_l>
				<amt_border_r>0.0</amt_border_r>
				<amt_border_kf>-1</amt_border_kf>
			</item>
			<item>
				<tx>-6.872005</tx>
				<ty>2.629088</ty>
				<tz>-0.788340</tz>
				<rx>0.000000</rx>
				<ry>-0.000000</ry>
				<rz>0.000000</rz>
				<state>1</state>
				<occlusion>-1</occlusion>
				<occlusion_kf>-1</occlusion_kf>
				<truncation>-1</truncation>
				<amt_occlusion>0.0</amt_occlusion>
				<amt_occlusion_kf>-1</amt_occlusion_kf>
				<amt_border_l>0.0</amt_border_l>
				<amt_border_r>0.0</amt_border_r>
				<amt_border_kf>-1</amt_border_kf>
			</item>
			<item>
				<tx>-7.091454</tx>
				<ty>2.603442</ty>
				<tz>-0.789174</tz>
				<rx>0.000000</rx>
				<ry>-0.000000</ry>
				<rz>0.000000</rz>
				<state>1</state>
				<occlusion>-1</occlusion>
				<occlusion_kf>-1</occlusion_kf>
				<truncation>-1</truncation>
				<amt_occlusion>0.0</amt_occlusion>
				<amt_occlusion_kf>-1</amt_occlusion_kf>
				<amt_border_l>0.0</amt_border_l>
				<amt_border_r>0.0</amt_border_r>
				<amt_border_kf>-1</amt_border_kf>
			</item>
			<item>
				<tx>-7.310863</tx>
				<ty>2.575575</ty>
				<tz>-0.790113</tz>
				<rx>0.000000</rx>
				<ry>-0.000000</ry>
				<rz>0.000000</rz>
				<state>1</state>
				<occlusion>-1</occlusion>
				<occlusion_kf>-1</occlusion_kf>
				<truncation>-1</truncation>
				<amt_occlusion>0.0</amt_occlusion>
				<amt_occlusion_kf>-1</amt_occlusion_kf>
				<amt_border_l>0.0</amt_border_l>
				<amt_border_r>0.0</amt_border_r>
				<amt_border_kf>-1</amt_border_kf>
			</item>
			<item>
				<tx>-7.535244</tx>
				<ty>2.542561</ty>
				<tz>-0.792180</tz>
				<rx>0.000000</rx>
				<ry>-0.000000</ry>
				<rz>0.000000</rz>
				<state>1</state>
				<occlusion>-1</occlusion>
				<occlusion_kf>-1</occlusion_kf>
				<truncation>-1</truncation>
				<amt_occlusion>0.0</amt_occlusion>
				<amt_occlusion_kf>-1</amt_occlusion_kf>
				<amt_border_l>0.0</amt_border_l>
				<amt_border_r>0.0</amt_border_r>
				<amt_border_kf>-1</amt_border_kf>
			</item>
			<item>
				<tx>-7.759634</tx>
				<ty>2.506868</ty>
				<tz>-0.794260</tz>
				<rx>0.000000</rx>
				<ry>-0.000000</ry>
				<rz>0.000000</rz>
				<state>1</state>
				<occlusion>-1</occlusion>
				<occlusion_kf>-1</occlusion_kf>
				<truncation>-1</truncation>
				<amt_occlusion>0.0</amt_occlusion>
				<amt_occlusion_kf>-1</amt_occlusion_kf>
				<amt_border_l>0.0</amt_border_l>
				<amt_border_r>0.0</amt_border_r>
				<amt_border_kf>-1</amt_border_kf>
			</item>
			<item>
				<tx>-7.982740</tx>
				<ty>2.478520</ty>
				<tz>-0.793617</tz>
				<rx>0.000000</rx>
				<ry>-0.000000</ry>
				<rz>0.000000</rz>
				<state>1</state>
				<occlusion>-1</occlusion>
				<occlusion_kf>-1</occlusion_kf>
				<truncation>-1</truncation>
				<amt_occlusion>0.0</amt_occlusion>
				<amt_occlusion_kf>-1</amt_occlusion_kf>
				<amt_border_l>0.0</amt_border_l>
				<amt_border_r>0.0</amt_border_r>
				<amt_border_kf>-1</amt_border_kf>
			</item>
			<item>
				<tx>-8.206710</tx>
				<ty>2.455252</ty>
				<tz>-0.791095</tz>
				<rx>0.000000</rx>
				<ry>-0.000000</ry>
				<rz>0.000000</rz>
				<state>1</state>
				<occlusion>-1</occlusion>
				<occlusion_kf>-1</occlusion_kf>
				<truncation>-1</truncation>
				<amt_occlusion>0.0</amt_occlusion>
				<amt_occlusion_kf>-1</amt_occlusion_kf>
				<amt_border_l>0.0</amt_border_l>
				<amt_border_r>0.0</amt_border_r>
				<amt_border_kf>-1</amt_border_kf>
			</item>
			<item>
				<tx>-8.428269</tx>
				<ty>2.432332</ty>
				<tz>-0.788735</tz>
				<rx>0.000000</rx>
				<ry>-0.000000</ry>
				<rz>0.000000</rz>
				<state>1</state>
				<occlusion>-1</occlusion>
				<occlusion_kf>-1</occlusion_kf>
				<truncation>-1</truncation>
				<amt_occlusion>0.0</amt_occlusion>
				<amt_occlusion_kf>-1</amt_occlusion_kf>
				<amt_border_l>0.0</amt_border_l>
				<amt_border_r>0.0</amt_border_r>
				<amt_border_kf>-1</amt_border_kf>
			</item>
			<item>
				<tx>-8.651071</tx>
				<ty>2.414744</ty>
				<tz>-0.786647</tz>
				<rx>0.000000</rx>
				<ry>-0.000000</ry>
				<rz>0.000000</rz>
				<state>1</state>
				<occlusion>-1</occlusion>
				<occlusion_kf>-1</occlusion_kf>
				<truncation>-1</truncation>
				<amt_occlusion>0.0</amt_occlusion>
				<amt_occlusion_kf>-1</amt_occlusion_kf>
				<amt_border_l>0.0</amt_border_l>
				<amt_border_r>0.0</amt_border_r>
				<amt_border_kf>-1</amt_border_kf>
			</item>
			<item>
				<tx>-8.872969</tx>
				<ty>2.396095</ty>
				<tz>-0.784566</tz>
				<rx>0.000000</rx>
				<ry>-0.000000</ry>
				<rz>0.000000</rz>
				<state>1</state>
				<occlusion>-1</occlusion>
				<occlusion_kf>-1</occlusion_kf>
				<truncation>-1</truncation>
				<amt_occlusion>0.0</amt_occlusion>
				<amt_occlusion_kf>-1</amt_occlusion_kf>
				<amt_border_l>0.0</amt_border_l>
				<amt_border_r>0.0</amt_border_r>
				<amt_border_kf>-1</amt_border_kf>
			</item>
			<item>
				<tx>-9.099732</tx>
				<ty>2.372083</ty>
				<tz>-0.782322</tz>
				<rx>0.000000</rx>
				<ry>-0.000000</ry>
				<rz>0.000000</rz>
				<state>1</state>
				<occlusion>-1</occlusion>
				<occlusion_kf>-1</occlusion_kf>
				<truncation>-1</truncation>
				<amt_occlusion>0.0</amt_occlusion>
				<amt_occlusion_kf>-1</amt_occlusion_kf>
				<amt_border_l>0.0</amt_border_l>
				<amt_border_r>0.0</amt_border_r>
				<amt_border_kf>-1</amt_border_kf>
			</item>
			<item>
				<tx>-9.327732</tx>
				<ty>2.345147</ty>
				<tz>-0.780245</tz>
				<rx>0.000000</rx>
				<ry>-0.000000</ry>
				<rz>0.000000</rz>
				<state>1</state>
				<occlusion>-1</occlusion>
				<occlusion_kf>-1</occlusion_kf>
				<truncation>-1</truncation>
				<amt_occlusion>0.0</amt_occlusion>
				<amt_occlusion_kf>-1</amt_occlusion_kf>
				<amt_border_l>0.0</amt_border_l>
				<amt_border_r>0.0</amt_border_r>
				<amt_border_kf>-1</amt_border_kf>
			</item>
			<item>
				<tx>-9.557902</tx>
				<ty>2.325236</ty>
				<tz>-0.778477</tz>
				<rx>0.000000</rx>
				<ry>-0.000000</ry>
				<rz>0.000000</rz>
				<state>1</state>
				<occlusion>-1</occlusion>
				<occlusion_kf>-1</occlusion_kf>
				<truncation>-1</truncation>
				<amt_occlusion>0.0</amt_occlusion>
				<amt_occlusion_kf>-1</amt_occlusion_kf>
				<amt_border_l>0.0</amt_border_l>
				<amt_border_r>0.0</amt_border_r>
				<amt_border_kf>-1</amt_border_kf>
			</item>
			<item>
				<tx>-9.794460</tx>
				<ty>2.313468</ty>
				<tz>-0.776981</tz>
				<rx>0.000000</rx>
				<ry>-0.000000</ry>
				<rz>0.000000</rz>
				<state>1</state>
				<occlusion>-1</occlusion>
				<occlusion_kf>-1</occlusion_kf>
				<truncation>-1</truncation>
				<amt_occlusion>0.0</amt_occlusion>
				<amt_occlusion_kf>-1</amt_occlusion_kf>
				<amt_border_l>0.0</amt_border_l>
				<amt_border_r>0.0</amt_border_r>
				<amt_border_kf>-1</amt_border_kf>
			</item>
			<item>
				<tx>-10.030950</tx>
				<ty>2.301609</ty>
				<tz>-0.775484</tz>
				<rx>0.000000</rx>
				<ry>-0.000000</ry>
				<rz>0.000000</rz>
				<state>1</state>
				<occlusion>-1</occlusion>
				<occlusion_kf>-1</occlusion_kf>
				<truncation>-1</truncation>
				<amt_occlusion>0.0</amt_occlusion>
				<amt_occlusion_kf>-1</amt_occlusion_kf>
				<amt_border_l>0.0</amt_border_l>
				<amt_border_r>0.0</amt_border_r>
				<amt_border_kf>-1</amt_border_kf>
			</item>
			<item>
				<tx>-10.274039</tx>
				<ty>2.288952</ty>
				<tz>-0.771277</tz>
				<rx>0.000000</rx>
				<ry>-0.000000</ry>
				<rz>0.000000</rz>
				<state>1</state>
				<occlusion>-1</occlusion>
				<occlusion_kf>-1</occlusion_kf>
				<truncation>-1</truncation>
				<amt_occlusion>0.0</amt_occlusion>
				<amt_occlusion_kf>-1</amt_occlusion_kf>
				<amt_border_l>0.0</amt_border_l>
				<amt_border_r>0.0</amt_border_r>
				<amt_border_kf>-1</amt_border_kf>
			</item>
			<item>
				<tx>-10.518250</tx>
				<ty>2.274365</ty>
				<tz>-0.766680</tz>
				<rx>0.000000</rx>
				<ry>-0.000000</ry>
				<rz>0.000000</rz>
				<state>1</state>
				<occlusion>-1</occlusion>
				<occlusion_kf>-1</occlusion_kf>
				<truncation>-1</truncation>
				<amt_occlusion>0.0</amt_occlusion>
				<amt_occlusion_kf>-1</amt_occlusion_kf>
				<amt_border_l>0.0</amt_border_l>
				<amt_border_r>0.0</amt_border_r>
				<amt_border_kf>-1</amt_border_kf>
			</item>
			<item>
				<tx>-10.725389</tx>
				<ty>2.264675</ty>
				<tz>-0.765100</tz>
				<rx>0.000000</rx>
				<ry>-0.000000</ry>
				<rz>0.000000</rz>
				<state>1</state>
				<occlusion>-1</occlusion>
				<occlusion_kf>-1</occlusion_kf>
				<truncation>-1</truncation>
				<amt_occlusion>0.0</amt_occlusion>
				<amt_occlusion_kf>-1</amt_occlusion_kf>
				<amt_border_l>0.0</amt_border_l>
				<amt_border_r>0.0</amt_border_r>
				<amt_border_kf>-1</amt_border_kf>
			</item>
			<item>
				<tx>-10.911274</tx>
				<ty>2.257952</ty>
				<tz>-0.765100</tz>
				<rx>0.000000</rx>
				<ry>-0.000000</ry>
				<rz>0.000000</rz>
				<state>1</state>
				<occlusion>-1</occlusion>
				<occlusion_kf>-1</occlusion_kf>
				<truncation>-1</truncation>
				<amt_occlusion>0.0</amt_occlusion>
				<amt_occlusion_kf>-1</amt_occlusion_kf>
				<amt_border_l>0.0</amt_border_l>
				<amt_border_r>0.0</amt_border_r>
				<amt_border_kf>-1</amt_border_kf>
			</item>
			<item>
				<tx>-11.096723</tx>
				<ty>2.250694</ty>
				<tz>-0.765100</tz>
				<rx>0.000000</rx>
				<ry>-0.000000</ry>
				<rz>0.000000</rz>
				<state>1</state>
				<occlusion>-1</occlusion>
				<occlusion_kf>-1</occlusion_kf>
				<truncation>-1</truncation>
				<amt_occlusion>0.0</amt_occlusion>
				<amt_occlusion_kf>-1</amt_occlusion_kf>
				<amt_border_l>0.0</amt_border_l>
				<amt_border_r>0.0</amt_border_r>
				<amt_border_kf>-1</amt_border_kf>
			</item>
			<item>
				<tx>-11.356271</tx>
				<ty>2.247300</ty>
				<tz>-0.765383</tz>
				<rx>0.000000</rx>
				<ry>-0.000000</ry>
				<rz>0.000000</rz>
				<state>1</state>
				<occlusion>-1</occlusion>
				<occlusion_kf>-1</occlusion_kf>
				<truncation>-1</truncation>
				<amt_occlusion>0.0</amt_occlusion>
				<amt_occlusion_kf>-1</amt_occlusion_kf>
				<amt_border_l>0.0</amt_border_l>
				<amt_border_r>0.0</amt_border_r>
				<amt_border_kf>-1</amt_border_kf>
			</item>
			<item>
				<tx>-11.692660</tx>
				<ty>2.243114</ty>
				<tz>-0.765958</tz>
				<rx>0.000000</rx>
				<ry>-0.000000</ry>
				<rz>0.000000</rz>
				<state>1</state>
				<occlusion>-1</occlusion>
				<occlusion_kf>-1</occlusion_kf>
				<truncation>-1</truncation>
				<amt_occlusion>0.0</amt_occlusion>
				<amt_occlusion_kf>-1</amt_occlusion_kf>
				<amt_border_l>0.0</amt_border_l>
				<amt_border_r>0.0</amt_border_r>
				<amt_border_kf>-1</amt_border_kf>
			</item>
			<item>
				<tx>-11.959110</tx>
				<ty>2.255532</ty>
				<tz>-0.766414</tz>
				<rx>0.000000</rx>
				<ry>-0.000000</ry>
				<rz>0.000000</rz>
				<state>1</state>
				<occlusion>-1</occlusion>
				<occlusion_kf>-1</occlusion_kf>
				<truncation>-1</truncation>
				<amt_occlusion>0.0</amt_occlusion>
				<amt_occlusion_kf>-1</amt_occlusion_kf>
				<amt_border_l>0.0</amt_border_l>
				<amt_border_r>0.0</amt_border_r>
				<amt_border_kf>-1</amt_border_kf>
			</item>
			<item>
				<tx>-12.200988</tx>
				<ty>2.274924</ty>
				<tz>-0.766829</tz>
				<rx>0.000000</rx>
				<ry>-0.000000</ry>
				<rz>0.000000</rz>
				<state>1</state>
				<occlusion>-1</occlusion>
				<occlusion_kf>-1</occlusion_kf>
				<truncation>-1</truncation>
				<amt_occlusion>0.0</amt_occlusion>
				<amt_occlusion_kf>-1</amt_occlusion_kf>
				<amt_border_l>0.0</amt_border_l>
				<amt_border_r>0.0</amt_border_r>
				<amt_border_kf>-1</amt_border_kf>
			</item>
			<item>
				<tx>-12.445189</tx>
				<ty>2.291397</ty>
				<tz>-0.765216</tz>
				<rx>0.000000</rx>
				<ry>-0.000000</ry>
				<rz>0.000000</rz>
				<state>1</state>
				<occlusion>-1</occlusion>
				<occlusion_kf>-1</occlusion_kf>
				<truncation>-1</truncation>
				<amt_occlusion>0.0</amt_occlusion>
				<amt_occlusion_kf>-1</amt_occlusion_kf>
				<amt_border_l>0.0</amt_border_l>
				<amt_border_r>0.0</amt_border_r>
				<amt_border_kf>-1</amt_border_kf>
			</item>
			<item>
				<tx>-12.692794</tx>
				<ty>2.309477</ty>
				<tz>-0.760212</tz>
				<rx>0.000000</rx>
				<ry>-0.000000</ry>
				<rz>0.000000</rz>
				<state>1</state>
				<occlusion>-1</occlusion>
				<occlusion_kf>-1</occlusion_kf>
				<truncation>-1</truncation>
				<amt_occlusion>0.0</amt_occlusion>
				<amt_occlusion_kf>-1</amt_occlusion_kf>
				<amt_border_l>0.0</amt_border_l>
				<amt_border_r>0.0</amt_border_r>
				<amt_border_kf>-1</amt_border_kf>
			</item>
			<item>
				<tx>-12.940497</tx>
				<ty>2.327080</ty>
				<tz>-0.755378</tz>
				<rx>0.000000</rx>
				<ry>-0.000000</ry>
				<rz>0.000000</rz>
				<state>1</state>
				<occlusion>-1</occlusion>
				<occlusion_kf>-1</occlusion_kf>
				<truncation>-1</truncation>
				<amt_occlusion>0.0</amt_occlusion>
				<amt_occlusion_kf>-1</amt_occlusion_kf>
				<amt_border_l>0.0</amt_border_l>
				<amt_border_r>0.0</amt_border_r>
				<amt_border_kf>-1</amt_border_kf>
			</item>
			<item>
				<tx>-13.192292</tx>
				<ty>2.343512</ty>
				<tz>-0.752807</tz>
				<rx>0.000000</rx>
				<ry>-0.000000</ry>
				<rz>0.000000</rz>
				<state>1</state>
				<occlusion>-1</occlusion>
				<occlusion_kf>-1</occlusion_kf>
				<truncation>-1</truncation>
				<amt_occlusion>0.0</amt_occlusion>
				<amt_occlusion_kf>-1</amt_occlusion_kf>
				<amt_border_l>0.0</amt_border_l>
				<amt_border_r>0.0</amt_border_r>
				<amt_border_kf>-1</amt_border_kf>
			</item>
			<item>
				<tx>-13.444398</tx>
				<ty>2.362676</ty>
				<tz>-0.750297</tz>
				<rx>0.000000</rx>
				<ry>-0.000000</ry>
				<rz>0.000000</rz>
				<state>1</state>
				<occlusion>-1</occlusion>
				<occlusion_kf>-1</occlusion_kf>
				<truncation>-1</truncation>
				<amt_occlusion>0.0</amt_occlusion>
				<amt_occlusion_kf>-1</amt_occlusion_kf>
				<amt_border_l>0.0</amt_border_l>
				<amt_border_r>0.0</amt_border_r>
				<amt_border_kf>-1</amt_border_kf>
			</item>
			<item>
				<tx>-13.701344</tx>
				<ty>2.373313</ty>
				<tz>-0.747190</tz>
				<rx>0.000000</rx>
				<ry>-0.000000</ry>
				<rz>0.000000</rz>
				<state>1</state>
				<occlusion>-1</occlusion>
				<occlusion_kf>-1</occlusion_kf>
				<truncation>-1</truncation>
				<amt_occlusion>0.0</amt_occlusion>
				<amt_occlusion_kf>-1</amt_occlusion_kf>
				<amt_border_l>0.0</amt_border_l>
				<amt_border_r>0.0</amt_border_r>
				<amt_border_kf>-1</amt_border_kf>
			</item>
			<item>
				<tx>-13.960239</tx>
				<ty>2.377954</ty>
				<tz>-0.743861</tz>
				<rx>0.000000</rx>
				<ry>-0.000000</ry>
				<rz>0.000000</rz>
				<state>1</state>
				<occlusion>-1</occlusion>
				<occlusion_kf>-1</occlusion_kf>
				<truncation>-1</truncation>
				<amt_occlusion>0.0</amt_occlusion>
				<amt_occlusion_kf>-1</amt_occlusion_kf>
				<amt_border_l>0.0</amt_border_l>
				<amt_border_r>0.0</amt_border_r>
				<amt_border_kf>-1</amt_border_kf>
			</item>
			<item>
				<tx>-14.218668</tx>
				<ty>2.385713</ty>
				<tz>-0.740651</tz>
				<rx>0.000000</rx>
				<ry>-0.000000</ry>
				<rz>0.000000</rz>
				<state>1</state>
				<occlusion>-1</occlusion>
				<occlusion_kf>-1</occlusion_kf>
				<truncation>-1</truncation>
				<amt_occlusion>0.0</amt_occlusion>
				<amt_occlusion_kf>-1</amt_occlusion_kf>
				<amt_border_l>0.0</amt_border_l>
				<amt_border_r>0.0</amt_border_r>
				<amt_border_kf>-1</amt_border_kf>
			</item>
			<item>
				<tx>-14.471464</tx>
				<ty>2.398739</ty>
				<tz>-0.738615</tz>
				<rx>0.000000</rx>
				<ry>-0.000000</ry>
				<rz>0.000000</rz>
				<state>1</state>
				<occlusion>-1</occlusion>
				<occlusion_kf>-1</occlusion_kf>
				<truncation>-1</truncation>
				<amt_occlusion>0.0</amt_occlusion>
				<amt_occlusion_kf>-1</amt_occlusion_kf>
				<amt_border_l>0.0</amt_border_l>
				<amt_border_r>0.0</amt_border_r>
				<amt_border_kf>-1</amt_border_kf>
			</item>
			<item>
				<tx>-14.724243</tx>
				<ty>2.412370</ty>
				<tz>-0.736579</tz>
				<rx>0.000000</rx>
				<ry>-0.000000</ry>
				<rz>0.000000</rz>
				<state>1</state>
				<occlusion>-1</occlusion>
				<occlusion_kf>-1</occlusion_kf>
				<truncation>-1</truncation>
				<amt_occlusion>0.0</amt_occlusion>
				<amt_occlusion_kf>-1</amt_occlusion_kf>
				<amt_border_l>0.0</amt_border_l>
				<amt_border_r>0.0</amt_border_r>
				<amt_border_kf>-1</amt_border_kf>
			</item>
			<item>
				<tx>-14.991459</tx>
				<ty>2.423103</ty>
				<tz>-0.734879</tz>
				<rx>0.000000</rx>
				<ry>-0.000000</ry>
				<rz>0.000000</rz>
				<state>1</state>
				<occlusion>-1</occlusion>
				<occlusion_kf>-1</occlusion_kf>
				<truncation>-1</truncation>
				<amt_occlusion>0.0</amt_occlusion>
				<amt_occlusion_kf>-1</amt_occlusion_kf>
				<amt_border_l>0.0</amt_border_l>
				<amt_border_r>0.0</amt_border_r>
				<amt_border_kf>-1</amt_border_kf>
			</item>
			<item>
				<tx>-15.267408</tx>
				<ty>2.424091</ty>
				<tz>-0.733187</tz>
				<rx>0.000000</rx>
				<ry>-0.000000</ry>
				<rz>0.000000</rz>
				<state>1</state>
				<occlusion>-1</occlusion>
				<occlusion_kf>-1</occlusion_kf>
				<truncation>-1</truncation>
				<amt_occlusion>0.0</amt_occlusion>
				<amt_occlusion_kf>-1</amt_occlusion_kf>
				<amt_border_l>0.0</amt_border_l>
				<amt_border_r>0.0</amt_border_r>
				<amt_border_kf>-1</amt_border_kf>
			</item>
			<item>
				<tx>-15.543209</tx>
				<ty>2.424997</ty>
				<tz>-0.730291</tz>
				<rx>0.000000</rx>
				<ry>-0.000000</ry>
				<rz>0.000000</rz>
				<state>1</state>
				<occlusion>-1</occlusion>
				<occlusion_kf>-1</occlusion_kf>
				<truncation>-1</truncation>
				<amt_occlusion>0.0</amt_occlusion>
				<amt_occlusion_kf>-1</amt_occlusion_kf>
				<amt_border_l>0.0</amt_border_l>
				<amt_border_r>0.0</amt_border_r>
				<amt_border_kf>-1</amt_border_kf>
			</item>
			<item>
				<tx>-15.818946</tx>
				<ty>2.421988</ty>
				<tz>-0.724302</tz>
				<rx>0.000000</rx>
				<ry>-0.000000</ry>
				<rz>0.000000</rz>
				<state>1</state>
				<occlusion>-1</occlusion>
				<occlusion_kf>-1</occlusion_kf>
				<truncation>-1</truncation>
				<amt_occlusion>0.0</amt_occlusion>
				<amt_occlusion_kf>-1</amt_occlusion_kf>
				<amt_border_l>0.0</amt_border_l>
				<amt_border_r>0.0</amt_border_r>
				<amt_border_kf>-1</amt_border_kf>
			</item>
			<item>
				<tx>-16.094646</tx>
				<ty>2.418603</ty>
				<tz>-0.718313</tz>
				<rx>0.000000</rx>
				<ry>-0.000000</ry>
				<rz>0.000000</rz>
				<state>1</state>
				<occlusion>-1</occlusion>
				<occlusion_kf>-1</occlusion_kf>
				<truncation>-1</truncation>
				<amt_occlusion>0.0</amt_occlusion>
				<amt_occlusion_kf>-1</amt_occlusion_kf>
				<amt_border_l>0.0</amt_border_l>
				<amt_border_r>0.0</amt_border_r>
				<amt_border_kf>-1</amt_border_kf>
			</item>
			<item>
				<tx>-16.366504</tx>
				<ty>2.437734</ty>
				<tz>-0.715479</tz>
				<rx>0.000000</rx>
				<ry>-0.000000</ry>
				<rz>0.000000</rz>
				<state>1</state>
				<occlusion>-1</occlusion>
				<occlusion_kf>-1</occlusion_kf>
				<truncation>-1</truncation>
				<amt_occlusion>0.0</amt_occlusion>
				<amt_occlusion_kf>-1</amt_occlusion_kf>
				<amt_border_l>0.0</amt_border_l>
				<amt_border_r>0.0</amt_border_r>
				<amt_border_kf>-1</amt_border_kf>
			</item>
			<item>
				<tx>-16.638757</tx>
				<ty>2.460581</ty>
				<tz>-0.715916</tz>
				<rx>0.000000</rx>
				<ry>-0.000000</ry>
				<rz>0.000000</rz>
				<state>1</state>
				<occlusion>-1</occlusion>
				<occlusion_kf>-1</occlusion_kf>
				<truncation>-1</truncation>
				<amt_occlusion>0.0</amt_occlusion>
				<amt_occlusion_kf>-1</amt_occlusion_kf>
				<amt_border_l>0.0</amt_border_l>
				<amt_border_r>0.0</amt_border_r>
				<amt_border_kf>-1</amt_border_kf>
			</item>
			<item>
				<tx>-16.880938</tx>
				<ty>2.476982</ty>
				<tz>-0.712961</tz>
				<rx>0.000000</rx>
				<ry>-0.000000</ry>
				<rz>0.000000</rz>
				<state>1</state>
				<occlusion>-1</occlusion>
				<occlusion_kf>-1</occlusion_kf>
				<truncation>-1</truncation>
				<amt_occlusion>0.0</amt_occlusion>
				<amt_occlusion_kf>-1</amt_occlusion_kf>
				<amt_border_l>0.0</amt_border_l>
				<amt_border_r>0.0</amt_border_r>
				<amt_border_kf>-1</amt_border_kf>
			</item>
			<item>
				<tx>-17.096292</tx>
				<ty>2.497461</ty>
				<tz>-0.709024</tz>
				<rx>0.000000</rx>
				<ry>-0.000000</ry>
				<rz>0.000000</rz>
				<state>1</state>
				<occlusion>-1</occlusion>
				<occlusion_kf>-1</occlusion_kf>
				<truncation>-1</truncation>
				<amt_occlusion>0.0</amt_occlusion>
				<amt_occlusion_kf>-1</amt_occlusion_kf>
				<amt_border_l>0.0</amt_border_l>
				<amt_border_r>0.0</amt_border_r>
				<amt_border_kf>-1</amt_border_kf>
			</item>
			<item>
				<tx>-17.312426</tx>
				<ty>2.518485</ty>
				<tz>-0.705077</tz>
				<rx>0.000000</rx>
				<ry>-0.000000</ry>
				<rz>0.000000</rz>
				<state>1</state>
				<occlusion>-1</occlusion>
				<occlusion_kf>-1</occlusion_kf>
				<truncation>-1</truncation>
				<amt_occlusion>0.0</amt_occlusion>
				<amt_occlusion_kf>-1</amt_occlusion_kf>
				<amt_border_l>0.0</amt_border_l>
				<amt_border_r>0.0</amt_border_r>
				<amt_border_kf>-1</amt_border_kf>
			</item>
			<item>
				<tx>-17.632635</tx>
				<ty>2.509397</ty>
				<tz>-0.676925</tz>
				<rx>0.000000</rx>
				<ry>-0.000000</ry>
				<rz>0.000000</rz>
				<state>1</state>
				<occlusion>-1</occlusion>
				<occlusion_kf>-1</occlusion_kf>
				<truncation>-1</truncation>
				<amt_occlusion>0.0</amt_occlusion>
				<amt_occlusion_kf>-1</amt_occlusion_kf>
				<amt_border_l>0.0</amt_border_l>
				<amt_border_r>0.0</amt_border_r>
				<amt_border_kf>-1</amt_border_kf>
			</item>
			<item>
				<tx>-17.990091</tx>
				<ty>2.477535</ty>
				<tz>-0.632697</tz>
				<rx>0.000000</rx>
				<ry>-0.000000</ry>
				<rz>0.000000</rz>
				<state>1</state>
				<occlusion>-1</occlusion>
				<occlusion_kf>-1</occlusion_kf>
				<truncation>-1</truncation>
				<amt_occlusion>0.0</amt_occlusion>
				<amt_occlusion_kf>-1</amt_occlusion_kf>
				<amt_border_l>0.0</amt_border_l>
				<amt_border_r>0.0</amt_border_r>
				<amt_border_kf>-1</amt_border_kf>
			</item>
			<item>
				<tx>-18.304615</tx>
				<ty>2.492939</ty>
				<tz>-0.613124</tz>
				<rx>0.000000</rx>
				<ry>-0.000000</ry>
				<rz>0.000000</rz>
				<state>1</state>
				<occlusion>-1</occlusion>
				<occlusion_kf>-1</occlusion_kf>
				<truncation>-1</truncation>
				<amt_occlusion>0.0</amt_occlusion>
				<amt_occlusion_kf>-1</amt_occlusion_kf>
				<amt_border_l>0.0</amt_border_l>
				<amt_border_r>0.0</amt_border_r>
				<amt_border_kf>-1</amt_border_kf>
			</item>
			<item>
				<tx>-18.594997</tx>
				<ty>2.517248</ty>
				<tz>-0.604936</tz>
				<rx>0.000000</rx>
				<ry>-0.000000</ry>
				<rz>0.000000</rz>
				<state>1</state>
				<occlusion>-1</occlusion>
				<occlusion_kf>-1</occlusion_kf>
				<truncation>-1</truncation>
				<amt_occlusion>0.0</amt_occlusion>
				<amt_occlusion_kf>-1</amt_occlusion_kf>
				<amt_border_l>0.0</amt_border_l>
				<amt_border_r>0.0</amt_border_r>
				<amt_border_kf>-1</amt_border_kf>
			</item>
			<item>
				<tx>-18.877358</tx>
				<ty>2.559637</ty>
				<tz>-0.598321</tz>
				<rx>0.000000</rx>
				<ry>-0.000000</ry>
				<rz>0.000000</rz>
				<state>1</state>
				<occlusion>-1</occlusion>
				<occlusion_kf>-1</occlusion_kf>
				<truncation>-1</truncation>
				<amt_occlusion>0.0</amt_occlusion>
				<amt_occlusion_kf>-1</amt_occlusion_kf>
				<amt_border_l>0.0</amt_border_l>
				<amt_border_r>0.0</amt_border_r>
				<amt_border_kf>-1</amt_border_kf>
			</item>
			<item>
				<tx>-19.162746</tx>
				<ty>2.634665</ty>
				<tz>-0.593602</tz>
				<rx>0.000000</rx>
				<ry>-0.000000</ry>
				<rz>0.000000</rz>
				<state>1</state>
				<occlusion>-1</occlusion>
				<occlusion_kf>-1</occlusion_kf>
				<truncation>-1</truncation>
				<amt_occlusion>0.0</amt_occlusion>
				<amt_occlusion_kf>-1</amt_occlusion_kf>
				<amt_border_l>0.0</amt_border_l>
				<amt_border_r>0.0</amt_border_r>
				<amt_border_kf>-1</amt_border_kf>
			</item>
			<item>
				<tx>-19.415948</tx>
				<ty>2.703428</ty>
				<tz>-0.589320</tz>
				<rx>0.000000</rx>
				<ry>-0.000000</ry>
				<rz>0.000000</rz>
				<state>1</state>
				<occlusion>-1</occlusion>
				<occlusion_kf>-1</occlusion_kf>
				<truncation>-1</truncation>
				<amt_occlusion>0.0</amt_occlusion>
				<amt_occlusion_kf>-1</amt_occlusion_kf>
				<amt_border_l>0.0</amt_border_l>
				<amt_border_r>0.0</amt_border_r>
				<amt_border_kf>-1</amt_border_kf>
			</item>
			<item>
				<tx>-19.695862</tx>
				<ty>2.757450</ty>
				<tz>-0.583149</tz>
				<rx>0.000000</rx>
				<ry>-0.000000</ry>
				<rz>0.000000</rz>
				<state>1</state>
				<occlusion>-1</occlusion>
				<occlusion_kf>-1</occlusion_kf>
				<truncation>-1</truncation>
				<amt_occlusion>0.0</amt_occlusion>
				<amt_occlusion_kf>-1</amt_occlusion_kf>
				<amt_border_l>0.0</amt_border_l>
				<amt_border_r>0.0</amt_border_r>
				<amt_border_kf>-1</amt_border_kf>
			</item>
			<item>
				<tx>-19.976320</tx>
				<ty>2.815592</ty>
				<tz>-0.576901</tz>
				<rx>0.000000</rx>
				<ry>-0.000000</ry>
				<rz>0.000000</rz>
				<state>1</state>
				<occlusion>-1</occlusion>
				<occlusion_kf>-1</occlusion_kf>
				<truncation>-1</truncation>
				<amt_occlusion>0.0</amt_occlusion>
				<amt_occlusion_kf>-1</amt_occlusion_kf>
				<amt_border_l>0.0</amt_border_l>
				<amt_border_r>0.0</amt_border_r>
				<amt_border_kf>-1</amt_border_kf>
			</item>
			<item>
				<tx>-20.256230</tx>
				<ty>2.887606</ty>
				<tz>-0.570517</tz>
				<rx>0.000000</rx>
				<ry>-0.000000</ry>
				<rz>0.000000</rz>
				<state>1</state>
				<occlusion>-1</occlusion>
				<occlusion_kf>-1</occlusion_kf>
				<truncation>-1</truncation>
				<amt_occlusion>0.0</amt_occlusion>
				<amt_occlusion_kf>-1</amt_occlusion_kf>
				<amt_border_l>0.0</amt_border_l>
				<amt_border_r>0.0</amt_border_r>
				<amt_border_kf>-1</amt_border_kf>
			</item>
			<item>
				<tx>-20.536477</tx>
				<ty>2.980930</ty>
				<tz>-0.563771</tz>
				<rx>0.000000</rx>
				<ry>-0.000000</ry>
				<rz>0.000000</rz>
				<state>1</state>
				<occlusion>-1</occlusion>
				<occlusion_kf>-1</occlusion_kf>
				<truncation>-1</truncation>
				<amt_occlusion>0.0</amt_occlusion>
				<amt_occlusion_kf>-1</amt_occlusion_kf>
				<amt_border_l>0.0</amt_border_l>
				<amt_border_r>0.0</amt_border_r>
				<amt_border_kf>-1</amt_border_kf>
			</item>
			<item>
				<tx>-20.815470</tx>
				<ty>3.074196</ty>
				<tz>-0.557390</tz>
				<rx>0.000000</rx>
				<ry>-0.000000</ry>
				<rz>0.000000</rz>
				<state>1</state>
				<occlusion>-1</occlusion>
				<occlusion_kf>-1</occlusion_kf>
				<truncation>-1</truncation>
				<amt_occlusion>0.0</amt_occlusion>
				<amt_occlusion_kf>-1</amt_occlusion_kf>
				<amt_border_l>0.0</amt_border_l>
				<amt_border_r>0.0</amt_border_r>
				<amt_border_kf>-1</amt_border_kf>
			</item>
			<item>
				<tx>-21.089803</tx>
				<ty>3.171442</ty>
				<tz>-0.553257</tz>
				<rx>0.000000</rx>
				<ry>-0.000000</ry>
				<rz>0.000000</rz>
				<state>1</state>
				<occlusion>-1</occlusion>
				<occlusion_kf>-1</occlusion_kf>
				<truncation>-1</truncation>
				<amt_occlusion>0.0</amt_occlusion>
				<amt_occlusion_kf>-1</amt_occlusion_kf>
				<amt_border_l>0.0</amt_border_l>
				<amt_border_r>0.0</amt_border_r>
				<amt_border_kf>-1</amt_border_kf>
			</item>
			<item>
				<tx>-21.363398</tx>
				<ty>3.272267</ty>
				<tz>-0.549125</tz>
				<rx>0.000000</rx>
				<ry>-0.000000</ry>
				<rz>0.000000</rz>
				<state>1</state>
				<occlusion>-1</occlusion>
				<occlusion_kf>-1</occlusion_kf>
				<truncation>-1</truncation>
				<amt_occlusion>0.0</amt_occlusion>
				<amt_occlusion_kf>-1</amt_occlusion_kf>
				<amt_border_l>0.0</amt_border_l>
				<amt_border_r>0.0</amt_border_r>
				<amt_border_kf>-1</amt_border_kf>
			</item>
			<item>
				<tx>-21.638824</tx>
				<ty>3.352857</ty>
				<tz>-0.544647</tz>
				<rx>0.000000</rx>
				<ry>-0.000000</ry>
				<rz>0.000000</rz>
				<state>1</state>
				<occlusion>-1</occlusion>
				<occlusion_kf>-1</occlusion_kf>
				<truncation>-1</truncation>
				<amt_occlusion>0.0</amt_occlusion>
				<amt_occlusion_kf>-1</amt_occlusion_kf>
				<amt_border_l>0.0</amt_border_l>
				<amt_border_r>0.0</amt_border_r>
				<amt_border_kf>-1</amt_border_kf>
			</item>
			<item>
				<tx>-21.914780</tx>
				<ty>3.437953</ty>
				<tz>-0.540104</tz>
				<rx>0.000000</rx>
				<ry>-0.000000</ry>
				<rz>0.000000</rz>
				<state>1</state>
				<occlusion>-1</occlusion>
				<occlusion_kf>-1</occlusion_kf>
				<truncation>-1</truncation>
				<amt_occlusion>0.0</amt_occlusion>
				<amt_occlusion_kf>-1</amt_occlusion_kf>
				<amt_border_l>0.0</amt_border_l>
				<amt_border_r>0.0</amt_border_r>
				<amt_border_kf>-1</amt_border_kf>
			</item>
			<item>
				<tx>-22.190001</tx>
				<ty>3.524441</ty>
				<tz>-0.535263</tz>
				<rx>0.000000</rx>
				<ry>-0.000000</ry>
				<rz>0.000000</rz>
				<state>1</state>
				<occlusion>-1</occlusion>
				<occlusion_kf>-1</occlusion_kf>
				<truncation>-1</truncation>
				<amt_occlusion>0.0</amt_occlusion>
				<amt_occlusion_kf>-1</amt_occlusion_kf>
				<amt_border_l>0.0</amt_border_l>
				<amt_border_r>0.0</amt_border_r>
				<amt_border_kf>-1</amt_border_kf>
			</item>
			<item>
				<tx>-22.462896</tx>
				<ty>3.672632</ty>
				<tz>-0.528782</tz>
				<rx>0.000000</rx>
				<ry>-0.000000</ry>
				<rz>0.000000</rz>
				<state>1</state>
				<occlusion>-1</occlusion>
				<occlusion_kf>-1</occlusion_kf>
				<truncation>-1</truncation>
				<amt_occlusion>0.0</amt_occlusion>
				<amt_occlusion_kf>-1</amt_occlusion_kf>
				<amt_border_l>0.0</amt_border_l>
				<amt_border_r>0.0</amt_border_r>
				<amt_border_kf>-1</amt_border_kf>
			</item>
			<item>
				<tx>-22.734371</tx>
				<ty>3.824959</ty>
				<tz>-0.522311</tz>
				<rx>0.000000</rx>
				<ry>-0.000000</ry>
				<rz>0.000000</rz>
				<state>1</state>
				<occlusion>-1</occlusion>
				<occlusion_kf>-1</occlusion_kf>
				<truncation>-1</truncation>
				<amt_occlusion>0.0</amt_occlusion>
				<amt_occlusion_kf>-1</amt_occlusion_kf>
				<amt_border_l>0.0</amt_border_l>
				<amt_border_r>0.0</amt_border_r>
				<amt_border_kf>-1</amt_border_kf>
			</item>
			<item>
				<tx>-23.007185</tx>
				<ty>3.941313</ty>
				<tz>-0.517866</tz>
				<rx>0.000000</rx>
				<ry>-0.000000</ry>
				<rz>0.000000</rz>
				<state>1</state>
				<occlusion>-1</occlusion>
				<occlusion_kf>-1</occlusion_kf>
				<truncation>-1</truncation>
				<amt_occlusion>0.0</amt_occlusion>
				<amt_occlusion_kf>-1</amt_occlusion_kf>
				<amt_border_l>0.0</amt_border_l>
				<amt_border_r>0.0</amt_border_r>
				<amt_border_kf>-1</amt_border_kf>
			</item>
			<item>
				<tx>-23.280632</tx>
				<ty>4.056036</ty>
				<tz>-0.514879</tz>
				<rx>0.000000</rx>
				<ry>-0.000000</ry>
				<rz>0.000000</rz>
				<state>1</state>
				<occlusion>-1</occlusion>
				<occlusion_kf>-1</occlusion_kf>
				<truncation>-1</truncation>
				<amt_occlusion>0.0</amt_occlusion>
				<amt_occlusion_kf>-1</amt_occlusion_kf>
				<amt_border_l>0.0</amt_border_l>
				<amt_border_r>0.0</amt_border_r>
				<amt_border_kf>-1</amt_border_kf>
			</item>
			<item>
				<tx>-23.518872</tx>
				<ty>4.169066</ty>
				<tz>-0.511565</tz>
				<rx>0.000000</rx>
				<ry>-0.000000</ry>
				<rz>0.000000</rz>
				<state>1</state>
				<occlusion>-1</occlusion>
				<occlusion_kf>-1</occlusion_kf>
				<truncation>-1</truncation>
				<amt_occlusion>0.0</amt_occlusion>
				<amt_occlusion_kf>-1</amt_occlusion_kf>
				<amt_border_l>0.0</amt_border_l>
				<amt_border_r>0.0</amt_border_r>
				<amt_border_kf>-1</amt_border_kf>
			</item>
			<item>
				<tx>-23.729195</tx>
				<ty>4.275628</ty>
				<tz>-0.508867</tz>
				<rx>0.000000</rx>
				<ry>-0.000000</ry>
				<rz>0.000000</rz>
				<state>1</state>
				<occlusion>-1</occlusion>
				<occlusion_kf>-1</occlusion_kf>
				<truncation>-1</truncation>
				<amt_occlusion>0.0</amt_occlusion>
				<amt_occlusion_kf>-1</amt_occlusion_kf>
				<amt_border_l>0.0</amt_border_l>
				<amt_border_r>0.0</amt_border_r>
				<amt_border_kf>-1</amt_border_kf>
			</item>
			<item>
				<tx>-23.939041</tx>
				<ty>4.383958</ty>
				<tz>-0.506044</tz>
				<rx>0.000000</rx>
				<ry>-0.000000</ry>
				<rz>0.000000</rz>
				<state>1</state>
				<occlusion>-1</occlusion>
				<occlusion_kf>-1</occlusion_kf>
				<truncation>-1</truncation>
				<amt_occlusion>0.0</amt_occlusion>
				<amt_occlusion_kf>-1</amt_occlusion_kf>
				<amt_border_l>0.0</amt_border_l>
				<amt_border_r>0.0</amt_border_r>
				<amt_border_kf>-1</amt_border_kf>
			</item>
			<item>
				<tx>-24.223677</tx>
				<ty>4.530302</ty>
				<tz>-0.501016</tz>
				<rx>0.000000</rx>
				<ry>-0.000000</ry>
				<rz>0.000000</rz>
				<state>1</state>
				<occlusion>-1</occlusion>
				<occlusion_kf>-1</occlusion_kf>
				<truncation>-1</truncation>
				<amt_occlusion>0.0</amt_occlusion>
				<amt_occlusion_kf>-1</amt_occlusion_kf>
				<amt_border_l>0.0</amt_border_l>
				<amt_border_r>0.0</amt_border_r>
				<amt_border_kf>-1</amt_border_kf>
			</item>
			<item>
				<tx>-24.587078</tx>
				<ty>4.728647</ty>
				<tz>-0.493903</tz>
				<rx>0.000000</rx>
				<ry>-0.000000</ry>
				<rz>0.000000</rz>
				<state>1</state>
				<occlusion>-1</occlusion>
				<occlusion_kf>-1</occlusion_kf>
				<truncation>-1</truncation>
				<amt_occlusion>0.0</amt_occlusion>
				<amt_occlusion_kf>-1</amt_occlusion_kf>
				<amt_border_l>0.0</amt_border_l>
				<amt_border_r>0.0</amt_border_r>
				<amt_border_kf>-1</amt_border_kf>
			</item>
			<item>
				<tx>-24.879016</tx>
				<ty>4.890803</ty>
				<tz>-0.488397</tz>
				<rx>0.000000</rx>
				<ry>-0.000000</ry>
				<rz>0.000000</rz>
				<state>1</state>
				<occlusion>-1</occlusion>
				<occlusion_kf>-1</occlusion_kf>
				<truncation>-1</truncation>
				<amt_occlusion>0.0</amt_occlusion>
				<amt_occlusion_kf>-1</amt_occlusion_kf>
				<amt_border_l>0.0</amt_border_l>
				<amt_border_r>0.0</amt_border_r>
				<amt_border_kf>-1</amt_border_kf>
			</item>
			<item>
				<tx>-25.137039</tx>
				<ty>5.074904</ty>
				<tz>-0.483387</tz>
				<rx>0.000000</rx>
				<ry>-0.000000</ry>
				<rz>0.000000</rz>
				<state>1</state>
				<occlusion>-1</occlusion>
				<occlusion_kf>-1</occlusion_kf>
				<truncation>-1</truncation>
				<amt_occlusion>0.0</amt_occlusion>
				<amt_occlusion_kf>-1</amt_occlusion_kf>
				<amt_border_l>0.0</amt_border_l>
				<amt_border_r>0.0</amt_border_r>
				<amt_border_kf>-1</amt_border_kf>
			</item>
			<item>
				<tx>-25.396068</tx>
				<ty>5.249882</ty>
				<tz>-0.478923</tz>
				<rx>0.000000</rx>
				<ry>-0.000000</ry>
				<rz>0.000000</rz>
				<state>1</state>
				<occlusion>-1</occlusion>
				<occlusion_kf>-1</occlusion_kf>
				<truncation>-1</truncation>
				<amt_occlusion>0.0</amt_occlusion>
				<amt_occlusion_kf>-1</amt_occlusion_kf>
				<amt_border_l>0.0</amt_border_l>
				<amt_border_r>0.0</amt_border_r>
				<amt_border_kf>-1</amt_border_kf>
			</item>
			<item>
				<tx>-25.656349</tx>
				<ty>5.414404</ty>
				<tz>-0.475179</tz>
				<rx>0.000000</rx>
				<ry>-0.000000</ry>
				<rz>0.000000</rz>
				<state>1</state>
				<occlusion>-1</occlusion>
				<occlusion_kf>-1</occlusion_kf>
				<truncation>-1</truncation>
				<amt_occlusion>0.0</amt_occlusion>
				<amt_occlusion_kf>-1</amt_occlusion_kf>
				<amt_border_l>0.0</amt_border_l>
				<amt_border_r>0.0</amt_border_r>
				<amt_border_kf>-1</amt_border_kf>
			</item>
			<item>
				<tx>-25.916486</tx>
				<ty>5.582109</ty>
				<tz>-0.471315</tz>
				<rx>0.000000</rx>
				<ry>-0.000000</ry>
				<rz>0.000000</rz>
				<state>1</state>
				<occlusion>-1</occlusion>
				<occlusion_kf>-1</occlusion_kf>
				<truncation>-1</truncation>
				<amt_occlusion>0.0</amt_occlusion>
				<amt_occlusion_kf>-1</amt_occlusion_kf>
				<amt_border_l>0.0</amt_border_l>
				<amt_border_r>0.0</amt_border_r>
				<amt_border_kf>-1</amt_border_kf>
			</item>
			<item>
				<tx>-26.177291</tx>
				<ty>5.747256</ty>
				<tz>-0.466708</tz>
				<rx>0.000000</rx>
				<ry>-0.000000</ry>
				<rz>0.000000</rz>
				<state>1</state>
				<occlusion>-1</occlusion>
				<occlusion_kf>-1</occlusion_kf>
				<truncation>-1</truncation>
				<amt_occlusion>0.0</amt_occlusion>
				<amt_occlusion_kf>-1</amt_occlusion_kf>
				<amt_border_l>0.0</amt_border_l>
				<amt_border_r>0.0</amt_border_r>
				<amt_border_kf>-1</amt_border_kf>
			</item>
			<item>
				<tx>-26.436919</tx>
				<ty>5.919459</ty>
				<tz>-0.462121</tz>
				<rx>0.000000</rx>
				<ry>-0.000000</ry>
				<rz>0.000000</rz>
				<state>1</state>
				<occlusion>-1</occlusion>
				<occlusion_kf>-1</occlusion_kf>
				<truncation>-1</truncation>
				<amt_occlusion>0.0</amt_occlusion>
				<amt_occlusion_kf>-1</amt_occlusion_kf>
				<amt_border_l>0.0</amt_border_l>
				<amt_border_r>0.0</amt_border_r>
				<amt_border_kf>-1</amt_border_kf>
			</item>
			<item>
				<tx>-26.707297</tx>
				<ty>6.053648</ty>
				<tz>-0.457783</tz>
				<rx>0.000000</rx>
				<ry>-0.000000</ry>
				<rz>0.000000</rz>
				<state>1</state>
				<occlusion>-1</occlusion>
				<occlusion_kf>-1</occlusion_kf>
				<truncation>-1</truncation>
				<amt_occlusion>0.0</amt_occlusion>
				<amt_occlusion_kf>-1</amt_occlusion_kf>
				<amt_border_l>0.0</amt_border_l>
				<amt_border_r>0.0</amt_border_r>
				<amt_border_kf>-1</amt_border_kf>
			</item>
			<item>
				<tx>-26.979290</tx>
				<ty>6.188683</ty>
				<tz>-0.453562</tz>
				<rx>0.000000</rx>
				<ry>-0.000000</ry>
				<rz>0.000000</rz>
				<state>1</state>
				<occlusion>-1</occlusion>
				<occlusion_kf>-1</occlusion_kf>
				<truncation>-1</truncation>
				<amt_occlusion>0.0</amt_occlusion>
				<amt_occlusion_kf>-1</amt_occlusion_kf>
				<amt_border_l>0.0</amt_border_l>
				<amt_border_r>0.0</amt_border_r>
				<amt_border_kf>-1</amt_border_kf>
			</item>
			<item>
				<tx>-27.248435</tx>
				<ty>6.317892</ty>
				<tz>-0.448472</tz>
				<rx>0.000000</rx>
				<ry>-0.000000</ry>
				<rz>0.000000</rz>
				<state>1</state>
				<occlusion>-1</occlusion>
				<occlusion_kf>-1</occlusion_kf>
				<truncation>-1</truncation>
				<amt_occlusion>0.0</amt_occlusion>
				<amt_occlusion_kf>-1</amt_occlusion_kf>
				<amt_border_l>0.0</amt_border_l>
				<amt_border_r>0.0</amt_border_r>
				<amt_border_kf>-1</amt_border_kf>
			</item>
			<item>
				<tx>-27.509800</tx>
				<ty>6.435147</ty>
				<tz>-0.438338</tz>
				<rx>0.000000</rx>
				<ry>-0.000000</ry>
				<rz>0.000000</rz>
				<state>1</state>
				<occlusion>-1</occlusion>
				<occlusion_kf>-1</occlusion_kf>
				<truncation>-1</truncation>
				<amt_occlusion>0.0</amt_occlusion>
				<amt_occlusion_kf>-1</amt_occlusion_kf>
				<amt_border_l>0.0</amt_border_l>
				<amt_border_r>0.0</amt_border_r>
				<amt_border_kf>-1</amt_border_kf>
			</item>
			<item>
				<tx>-27.769222</tx>
				<ty>6.557077</ty>
				<tz>-0.428236</tz>
				<rx>0.000000</rx>
				<ry>-0.000000</ry>
				<rz>0.000000</rz>
				<state>1</state>
				<occlusion>-1</occlusion>
				<occlusion_kf>-1</occlusion_kf>
				<truncation>-1</truncation>
				<amt_occlusion>0.0</amt_occlusion>
				<amt_occlusion_kf>-1</amt_occlusion_kf>
				<amt_border_l>0.0</amt_border_l>
				<amt_border_r>0.0</amt_border_r>
				<amt_border_kf>-1</amt_border_kf>
			</item>
			<item>
				<tx>-28.041520</tx>
				<ty>6.674014</ty>
				<tz>-0.416885</tz>
				<rx>0.000000</rx>
				<ry>-0.000000</ry>
				<rz>0.000000</rz>
				<state>1</state>
				<occlusion>-1</occlusion>
				<occlusion_kf>-1</occlusion_kf>
				<truncation>-1</truncation>
				<amt_occlusion>0.0</amt_occlusion>
				<amt_occlusion_kf>-1</amt_occlusion_kf>
				<amt_border_l>0.0</amt_border_l>
				<amt_border_r>0.0</amt_border_r>
				<amt_border_kf>-1</amt_border_kf>
			</item>
			<item>
				<tx>-28.319265</tx>
				<ty>6.786161</ty>
				<tz>-0.404899</tz>
				<rx>0.000000</rx>
				<ry>-0.000000</ry>
				<rz>0.000000</rz>
				<state>1</state>
				<occlusion>-1</occlusion>
				<occlusion_kf>-1</occlusion_kf>
				<truncation>-1</truncation>
				<amt_occlusion>0.0</amt_occlusion>
				<amt_occlusion_kf>-1</amt_occlusion_kf>
				<amt_border_l>0.0</amt_border_l>
				<amt_border_r>0.0</amt_border_r>
				<amt_border_kf>-1</amt_border_kf>
			</item>
			<item>
				<tx>-28.600111</tx>
				<ty>6.878541</ty>
				<tz>-0.392121</tz>
				<rx>0.000000</rx>
				<ry>-0.000000</ry>
				<rz>0.000000</rz>
				<state>1</state>
				<occlusion>-1</occlusion>
				<occlusion_kf>-1</occlusion_kf>
				<truncation>-1</truncation>
				<amt_occlusion>0.0</amt_occlusion>
				<amt_occlusion_kf>-1</amt_occlusion_kf>
				<amt_border_l>0.0</amt_border_l>
				<amt_border_r>0.0</amt_border_r>
				<amt_border_kf>-1</amt_border_kf>
			</item>
			<item>
				<tx>-28.882921</tx>
				<ty>6.954422</ty>
				<tz>-0.377509</tz>
				<rx>0.000000</rx>
				<ry>-0.000000</ry>
				<rz>0.000000</rz>
				<state>1</state>
				<occlusion>-1</occlusion>
				<occlusion_kf>-1</occlusion_kf>
				<truncation>-1</truncation>
				<amt_occlusion>0.0</amt_occlusion>
				<amt_occlusion_kf>-1</amt_occlusion_kf>
				<amt_border_l>0.0</amt_border_l>
				<amt_border_r>0.0</amt_border_r>
				<amt_border_kf>-1</amt_border_kf>
			</item>
			<item>
				<tx>-29.165647</tx>
				<ty>7.029554</ty>
				<tz>-0.362920</tz>
				<rx>0.000000</rx>
				<ry>-0.000000</ry>
				<rz>0.000000</rz>
				<state>1</state>
				<occlusion>-1</occlusion>
				<occlusion_kf>-1</occlusion_kf>
				<truncation>-1</truncation>
				<amt_occlusion>0.0</amt_occlusion>
				<amt_occlusion_kf>-1</amt_occlusion_kf>
				<amt_border_l>0.0</amt_border_l>
				<amt_border_r>0.0</amt_border_r>
				<amt_border_kf>-1</amt_border_kf>
			</item>
			<item>
				<tx>-29.436287</tx>
				<ty>7.135165</ty>
				<tz>-0.349947</tz>
				<rx>0.000000</rx>
				<ry>-0.000000</ry>
				<rz>0.000000</rz>
				<state>1</state>
				<occlusion>-1</occlusion>
				<occlusion_kf>-1</occlusion_kf>
				<truncation>-1</truncation>
				<amt_occlusion>0.0</amt_occlusion>
				<amt_occlusion_kf>-1</amt_occlusion_kf>
				<amt_border_l>0.0</amt_border_l>
				<amt_border_r>0.0</amt_border_r>
				<amt_border_kf>-1</amt_border_kf>
			</item>
			<item>
				<tx>-29.705754</tx>
				<ty>7.246274</ty>
				<tz>-0.339963</tz>
				<rx>0.000000</rx>
				<ry>-0.000000</ry>
				<rz>0.000000</rz>
				<state>1</state>
				<occlusion>-1</occlusion>
				<occlusion_kf>-1</occlusion_kf>
				<truncation>-1</truncation>
				<amt_occlusion>0.0</amt_occlusion>
				<amt_occlusion_kf>-1</amt_occlusion_kf>
				<amt_border_l>0.0</amt_border_l>
				<amt_border_r>0.0</amt_border_r>
				<amt_border_kf>-1</amt_border_kf>
			</item>
			<item>
				<tx>-29.937860</tx>
				<ty>7.358109</ty>
				<tz>-0.328999</tz>
				<rx>0.000000</rx>
				<ry>-0.000000</ry>
				<rz>0.000000</rz>
				<state>1</state>
				<occlusion>-1</occlusion>
				<occlusion_kf>-1</occlusion_kf>
				<truncation>-1</truncation>
				<amt_occlusion>0.0</amt_occlusion>
				<amt_occlusion_kf>-1</amt_occlusion_kf>
				<amt_border_l>0.0</amt_border_l>
				<amt_border_r>0.0</amt_border_r>
				<amt_border_kf>-1</amt_border_kf>
			</item>
			<item>
				<tx>-30.140230</tx>
				<ty>7.478188</ty>
				<tz>-0.318481</tz>
				<rx>0.000000</rx>
				<ry>-0.000000</ry>
				<rz>0.000000</rz>
				<state>1</state>
				<occlusion>-1</occlusion>
				<occlusion_kf>-1</occlusion_kf>
				<truncation>-1</truncation>
				<amt_occlusion>0.0</amt_occlusion>
				<amt_occlusion_kf>-1</amt_occlusion_kf>
				<amt_border_l>0.0</amt_border_l>
				<amt_border_r>0.0</amt_border_r>
				<amt_border_kf>-1</amt_border_kf>
			</item>
			<item>
				<tx>-30.341938</tx>
				<ty>7.600077</ty>
				<tz>-0.307977</tz>
				<rx>0.000000</rx>
				<ry>-0.000000</ry>
				<rz>0.000000</rz>
				<state>1</state>
				<occlusion>-1</occlusion>
				<occlusion_kf>-1</occlusion_kf>
				<truncation>-1</truncation>
				<amt_occlusion>0.0</amt_occlusion>
				<amt_occlusion_kf>-1</amt_occlusion_kf>
				<amt_border_l>0.0</amt_border_l>
				<amt_border_r>0.0</amt_border_r>
				<amt_border_kf>-1</amt_border_kf>
			</item>
			<item>
				<tx>-30.617730</tx>
				<ty>7.731468</ty>
				<tz>-0.294731</tz>
				<rx>0.000000</rx>
				<ry>-0.000000</ry>
				<rz>0.000000</rz>
				<state>1</state>
				<occlusion>-1</occlusion>
				<occlusion_kf>-1</occlusion_kf>
				<truncation>-1</truncation>
				<amt_occlusion>0.0</amt_occlusion>
				<amt_occlusion_kf>-1</amt_occlusion_kf>
				<amt_border_l>0.0</amt_border_l>
				<amt_border_r>0.0</amt_border_r>
				<amt_border_kf>-1</amt_border_kf>
			</item>
			<item>
				<tx>-30.963426</tx>
				<ty>7.882202</ty>
				<tz>-0.278800</tz>
				<rx>0.000000</rx>
				<ry>-0.000000</ry>
				<rz>0.000000</rz>
				<state>1</state>
				<occlusion>-1</occlusion>
				<occlusion_kf>-1</occlusion_kf>
				<truncation>-1</truncation>
				<amt_occlusion>0.0</amt_occlusion>
				<amt_occlusion_kf>-1</amt_occlusion_kf>
				<amt_border_l>0.0</amt_border_l>
				<amt_border_r>0.0</amt_border_r>
				<amt_border_kf>-1</amt_border_kf>
			</item>
			<item>
				<tx>-31.276956</tx>
				<ty>7.991373</ty>
				<tz>-0.266504</tz>
				<rx>0.000000</rx>
				<ry>-0.000000</ry>
				<rz>0.000000</rz>
				<state>1</state>
				<occlusion>-1</occlusion>
				<occlusion_kf>-1</occlusion_kf>
				<truncation>-1</truncation>
				<amt_occlusion>0.0</amt_occlusion>
				<amt_occlusion_kf>-1</amt_occlusion_kf>
				<amt_border_l>0.0</amt_border_l>
				<amt_border_r>0.0</amt_border_r>
				<amt_border_kf>-1</amt_border_kf>
			</item>
			<item>
				<tx>-31.566845</tx>
				<ty>8.097913</ty>
				<tz>-0.255927</tz>
				<rx>0.000000</rx>
				<ry>-0.000000</ry>
				<rz>0.000000</rz>
				<state>1</state>
				<occlusion>-1</occlusion>
				<occlusion_kf>-1</occlusion_kf>
				<truncation>-1</truncation>
				<amt_occlusion>0.0</amt_occlusion>
				<amt_occlusion_kf>-1</amt_occlusion_kf>
				<amt_border_l>0.0</amt_border_l>
				<amt_border_r>0.0</amt_border_r>
				<amt_border_kf>-1</amt_border_kf>
			</item>
			<item>
				<tx>-31.863672</tx>
				<ty>8.222909</ty>
				<tz>-0.242090</tz>
				<rx>0.000000</rx>
				<ry>-0.000000</ry>
				<rz>0.000000</rz>
				<state>1</state>
				<occlusion>-1</occlusion>
				<occlusion_kf>-1</occlusion_kf>
				<truncation>-1</truncation>
				<amt_occlusion>0.0</amt_occlusion>
				<amt_occlusion_kf>-1</amt_occlusion_kf>
				<amt_border_l>0.0</amt_border_l>
				<amt_border_r>0.0</amt_border_r>
				<amt_border_kf>-1</amt_border_kf>
			</item>
			<item>
				<tx>-32.111514</tx>
				<ty>8.366043</ty>
				<tz>-0.226743</tz>
				<rx>0.000000</rx>
				<ry>-0.000000</ry>
				<rz>0.000000</rz>
				<state>1</state>
				<occlusion>-1</occlusion>
				<occlusion_kf>-1</occlusion_kf>
				<truncation>-1</truncation>
				<amt_occlusion>0.0</amt_occlusion>
				<amt_occlusion_kf>-1</amt_occlusion_kf>
				<amt_border_l>0.0</amt_border_l>
				<amt_border_r>0.0</amt_border_r>
				<amt_border_kf>-1</amt_border_kf>
			</item>
			<item>
				<tx>-32.374332</tx>
				<ty>8.514298</ty>
				<tz>-0.210702</tz>
				<rx>0.000000</rx>
				<ry>-0.000000</ry>
				<rz>0.000000</rz>
				<state>1</state>
				<occlusion>-1</occlusion>
				<occlusion_kf>-1</occlusion_kf>
				<truncation>-1</truncation>
				<amt_occlusion>0.0</amt_occlusion>
				<amt_occlusion_kf>-1</amt_occlusion_kf>
				<amt_border_l>0.0</amt_border_l>
				<amt_border_r>0.0</amt_border_r>
				<amt_border_kf>-1</amt_border_kf>
			</item>
			<item>
				<tx>-32.643304</tx>
				<ty>8.643667</ty>
				<tz>-0.198075</tz>
				<rx>0.000000</rx>
				<ry>-0.000000</ry>
				<rz>0.000000</rz>
				<state>1</state>
				<occlusion>-1</occlusion>
				<occlusion_kf>-1</occlusion_kf>
				<truncation>-1</truncation>
				<amt_occlusion>0.0</amt_occlusion>
				<amt_occlusion_kf>-1</amt_occlusion_kf>
				<amt_border_l>0.0</amt_border_l>
				<amt_border_r>0.0</amt_border_r>
				<amt_border_kf>-1</amt_border_kf>
			</item>
			<item>
				<tx>-32.909581</tx>
				<ty>8.778708</ty>
				<tz>-0.185585</tz>
				<rx>0.000000</rx>
				<ry>-0.000000</ry>
				<rz>0.000000</rz>
				<state>1</state>
				<occlusion>-1</occlusion>
				<occlusion_kf>-1</occlusion_kf>
				<truncation>-1</truncation>
				<amt_occlusion>0.0</amt_occlusion>
				<amt_occlusion_kf>-1</amt_occlusion_kf>
				<amt_border_l>0.0</amt_border_l>
				<amt_border_r>0.0</amt_border_r>
				<amt_border_kf>-1</amt_border_kf>
			</item>
			<item>
				<tx>-33.195459</tx>
				<ty>8.915089</ty>
				<tz>-0.172246</tz>
				<rx>0.000000</rx>
				<ry>-0.000000</ry>
				<rz>0.000000</rz>
				<state>1</state>
				<occlusion>-1</occlusion>
				<occlusion_kf>-1</occlusion_kf>
				<truncation>-1</truncation>
				<amt_occlusion>0.0</amt_occlusion>
				<amt_occlusion_kf>-1</amt_occlusion_kf>
				<amt_border_l>0.0</amt_border_l>
				<amt_border_r>0.0</amt_border_r>
				<amt_border_kf>-1</amt_border_kf>
			</item>
			<item>
				<tx>-33.447972</tx>
				<ty>9.044011</ty>
				<tz>-0.160354</tz>
				<rx>0.000000</rx>
				<ry>-0.000000</ry>
				<rz>0.000000</rz>
				<state>1</state>
				<occlusion>-1</occlusion>
				<occlusion_kf>-1</occlusion_kf>
				<truncation>-1</truncation>
				<amt_occlusion>0.0</amt_occlusion>
				<amt_occlusion_kf>-1</amt_occlusion_kf>
				<amt_border_l>0.0</amt_border_l>
				<amt_border_r>0.0</amt_border_r>
				<amt_border_kf>-1</amt_border_kf>
			</item>
			<item>
				<tx>-33.714751</tx>
				<ty>9.185614</ty>
				<tz>-0.147788</tz>
				<rx>0.000000</rx>
				<ry>-0.000000</ry>
				<rz>0.000000</rz>
				<state>1</state>
				<occlusion>-1</occlusion>
				<occlusion_kf>-1</occlusion_kf>
				<truncation>-1</truncation>
				<amt_occlusion>0.0</amt_occlusion>
				<amt_occlusion_kf>-1</amt_occlusion_kf>
				<amt_border_l>0.0</amt_border_l>
				<amt_border_r>0.0</amt_border_r>
				<amt_border_kf>-1</amt_border_kf>
			</item>
			<item>
				<tx>-33.971296</tx>
				<ty>9.344792</ty>
				<tz>-0.135682</tz>
				<rx>0.000000</rx>
				<ry>-0.000000</ry>
				<rz>0.000000</rz>
				<state>1</state>
				<occlusion>-1</occlusion>
				<occlusion_kf>-1</occlusion_kf>
				<truncation>-1</truncation>
				<amt_occlusion>0.0</amt_occlusion>
				<amt_occlusion_kf>-1</amt_occlusion_kf>
				<amt_border_l>0.0</amt_border_l>
				<amt_border_r>0.0</amt_border_r>
				<amt_border_kf>-1</amt_border_kf>
			</item>
			<item>
				<tx>-34.225882</tx>
				<ty>9.507156</ty>
				<tz>-0.123618</tz>
				<rx>0.000000</rx>
				<ry>-0.000000</ry>
				<rz>0.000000</rz>
				<state>1</state>
				<occlusion>-1</occlusion>
				<occlusion_kf>-1</occlusion_kf>
				<truncation>-1</truncation>
				<amt_occlusion>0.0</amt_occlusion>
				<amt_occlusion_kf>-1</amt_occlusion_kf>
				<amt_border_l>0.0</amt_border_l>
				<amt_border_r>0.0</amt_border_r>
				<amt_border_kf>-1</amt_border_kf>
			</item>
			<item>
				<tx>-34.496078</tx>
				<ty>9.669108</ty>
				<tz>-0.109161</tz>
				<rx>0.000000</rx>
				<ry>-0.000000</ry>
				<rz>0.000000</rz>
				<state>1</state>
				<occlusion>-1</occlusion>
				<occlusion_kf>-1</occlusion_kf>
				<truncation>-1</truncation>
				<amt_occlusion>0.0</amt_occlusion>
				<amt_occlusion_kf>-1</amt_occlusion_kf>
				<amt_border_l>0.0</amt_border_l>
				<amt_border_r>0.0</amt_border_r>
				<amt_border_kf>-1</amt_border_kf>
			</item>
			<item>
				<tx>-34.735532</tx>
				<ty>9.816714</ty>
				<tz>-0.095906</tz>
				<rx>0.000000</rx>
				<ry>-0.000000</ry>
				<rz>0.000000</rz>
				<state>1</state>
				<occlusion>-1</occlusion>
				<occlusion_kf>-1</occlusion_kf>
				<truncation>-1</truncation>
				<amt_occlusion>0.0</amt_occlusion>
				<amt_occlusion_kf>-1</amt_occlusion_kf>
				<amt_border_l>0.0</amt_border_l>
				<amt_border_r>0.0</amt_border_r>
				<amt_border_kf>-1</amt_border_kf>
			</item>
			<item>
				<tx>-34.986184</tx>
				<ty>9.986550</ty>
				<tz>-0.082273</tz>
				<rx>0.000000</rx>
				<ry>-0.000000</ry>
				<rz>0.000000</rz>
				<state>1</state>
				<occlusion>-1</occlusion>
				<occlusion_kf>-1</occlusion_kf>
				<truncation>-1</truncation>
				<amt_occlusion>0.0</amt_occlusion>
				<amt_occlusion_kf>-1</amt_occlusion_kf>
				<amt_border_l>0.0</amt_border_l>
				<amt_border_r>0.0</amt_border_r>
				<amt_border_kf>-1</amt_border_kf>
			</item>
			<item>
				<tx>-35.227921</tx>
				<ty>10.202436</ty>
				<tz>-0.069193</tz>
				<rx>0.000000</rx>
				<ry>-0.000000</ry>
				<rz>0.000000</rz>
				<state>1</state>
				<occlusion>-1</occlusion>
				<occlusion_kf>-1</occlusion_kf>
				<truncation>-1</truncation>
				<amt_occlusion>0.0</amt_occlusion>
				<amt_occlusion_kf>-1</amt_occlusion_kf>
				<amt_border_l>0.0</amt_border_l>
				<amt_border_r>0.0</amt_border_r>
				<amt_border_kf>-1</amt_border_kf>
			</item>
			<item>
				<tx>-35.469484</tx>
				<ty>10.418017</ty>
				<tz>-0.056111</tz>
				<rx>0.000000</rx>
				<ry>-0.000000</ry>
				<rz>0.000000</rz>
				<state>1</state>
				<occlusion>-1</occlusion>
				<occlusion_kf>-1</occlusion_kf>
				<truncation>-1</truncation>
				<amt_occlusion>0.0</amt_occlusion>
				<amt_occlusion_kf>-1</amt_occlusion_kf>
				<amt_border_l>0.0</amt_border_l>
				<amt_border_r>0.0</amt_border_r>
				<amt_border_kf>-1</amt_border_kf>
			</item>
			<item>
				<tx>-35.684321</tx>
				<ty>10.690864</ty>
				<tz>-0.045800</tz>
				<rx>0.000000</rx>
				<ry>-0.000000</ry>
				<rz>0.000000</rz>
				<state>1</state>
				<occlusion>-1</occlusion>
				<occlusion_kf>-1</occlusion_kf>
				<truncation>-1</truncation>
				<amt_occlusion>0.0</amt_occlusion>
				<amt_occlusion_kf>-1</amt_occlusion_kf>
				<amt_border_l>0.0</amt_border_l>
				<amt_border_r>0.0</amt_border_r>
				<amt_border_kf>-1</amt_border_kf>
			</item>
			<item>
				<tx>-35.897180</tx>
				<ty>10.968726</ty>
				<tz>-0.035475</tz>
				<rx>0.000000</rx>
				<ry>-0.000000</ry>
				<rz>0.000000</rz>
				<state>1</state>
				<occlusion>-1</occlusion>
				<occlusion_kf>-1</occlusion_kf>
				<truncation>-1</truncation>
				<amt_occlusion>0.0</amt_occlusion>
				<amt_occlusion_kf>-1</amt_occlusion_kf>
				<amt_border_l>0.0</amt_border_l>
				<amt_border_r>0.0</amt_border_r>
				<amt_border_kf>-1</amt_border_kf>
			</item>
			<item>
				<tx>-36.076267</tx>
				<ty>11.239589</ty>
				<tz>-0.028411</tz>
				<rx>0.000000</rx>
				<ry>-0.000000</ry>
				<rz>0.000000</rz>
				<state>1</state>
				<occlusion>-1</occlusion>
				<occlusion_kf>-1</occlusion_kf>
				<truncation>-1</truncation>
				<amt_occlusion>0.0</amt_occlusion>
				<amt_occlusion_kf>-1</amt_occlusion_kf>
				<amt_border_l>0.0</amt_border_l>
				<amt_border_r>0.0</amt_border_r>
				<amt_border_kf>-1</amt_border_kf>
			</item>
			<item>
				<tx>-36.228440</tx>
				<ty>11.509062</ty>
				<tz>-0.023755</tz>
				<rx>0.000000</rx>
				<ry>-0.000000</ry>
				<rz>0.000000</rz>
				<state>1</state>
				<occlusion>-1</occlusion>
				<occlusion_kf>-1</occlusion_kf>
				<truncation>-1</truncation>
				<amt_occlusion>0.0</amt_occlusion>
				<amt_occlusion_kf>-1</amt_occlusion_kf>
				<amt_border_l>0.0</amt_border_l>
				<amt_border_r>0.0</amt_border_r>
				<amt_border_kf>-1</amt_border_kf>
			</item>
			<item>
				<tx>-36.378954</tx>
				<ty>11.779356</ty>
				<tz>-0.019105</tz>
				<rx>0.000000</rx>
				<ry>-0.000000</ry>
				<rz>0.000000</rz>
				<state>1</state>
				<occlusion>-1</occlusion>
				<occlusion_kf>-1</occlusion_kf>
				<truncation>-1</truncation>
				<amt_occlusion>0.0</amt_occlusion>
				<amt_occlusion_kf>-1</amt_occlusion_kf>
				<amt_border_l>0.0</amt_border_l>
				<amt_border_r>0.0</amt_border_r>
				<amt_border_kf>-1</amt_border_kf>
			</item>
			<item>
				<tx>-36.591087</tx>
				<ty>12.200226</ty>
				<tz>-0.012888</tz>
				<rx>0.000000</rx>
				<ry>-0.000000</ry>
				<rz>0.000000</rz>
				<state>1</state>
				<occlusion>-1</occlusion>
				<occlusion_kf>-1</occlusion_kf>
				<truncation>-1</truncation>
				<amt_occlusion>0.0</amt_occlusion>
				<amt_occlusion_kf>-1</amt_occlusion_kf>
				<amt_border_l>0.0</amt_border_l>
				<amt_border_r>0.0</amt_border_r>
				<amt_border_kf>-1</amt_border_kf>
			</item>
			<item>
				<tx>-36.804099</tx>
				<ty>12.675707</ty>
				<tz>-0.006555</tz>
				<rx>0.000000</rx>
				<ry>-0.000000</ry>
				<rz>0.000000</rz>
				<state>1</state>
				<occlusion>-1</occlusion>
				<occlusion_kf>-1</occlusion_kf>
				<truncation>-1</truncation>
				<amt_occlusion>0.0</amt_occlusion>
				<amt_occlusion_kf>-1</amt_occlusion_kf>
				<amt_border_l>0.0</amt_border_l>
				<amt_border_r>0.0</amt_border_r>
				<amt_border_kf>-1</amt_border_kf>
			</item>
			<item>
				<tx>-36.989099</tx>
				<ty>13.056320</ty>
				<tz>0.000785</tz>
				<rx>0.000000</rx>
				<ry>-0.000000</ry>
				<rz>0.000000</rz>
				<state>1</state>
				<occlusion>-1</occlusion>
				<occlusion_kf>-1</occlusion_kf>
				<truncation>-1</truncation>
				<amt_occlusion>0.0</amt_occlusion>
				<amt_occlusion_kf>-1</amt_occlusion_kf>
				<amt_border_l>0.0</amt_border_l>
				<amt_border_r>0.0</amt_border_r>
				<amt_border_kf>-1</amt_border_kf>
			</item>
			<item>
				<tx>-37.149913</tx>
				<ty>13.435275</ty>
				<tz>0.008297</tz>
				<rx>0.000000</rx>
				<ry>-0.000000</ry>
				<rz>0.000000</rz>
				<state>1</state>
				<occlusion>-1</occlusion>
				<occlusion_kf>-1</occlusion_kf>
				<truncation>-1</truncation>
				<amt_occlusion>0.0</amt_occlusion>
				<amt_occlusion_kf>-1</amt_occlusion_kf>
				<amt_border_l>0.0</amt_border_l>
				<amt_border_r>0.0</amt_border_r>
				<amt_border_kf>-1</amt_border_kf>
			</item>
			<item>
				<tx>-37.305082</tx>
				<ty>13.815976</ty>
				<tz>0.015629</tz>
				<rx>0.000000</rx>
				<ry>-0.000000</ry>
				<rz>0.000000</rz>
				<state>1</state>
				<occlusion>-1</occlusion>
				<occlusion_kf>-1</occlusion_kf>
				<truncation>-1</truncation>
				<amt_occlusion>0.0</amt_occlusion>
				<amt_occlusion_kf>-1</amt_occlusion_kf>
				<amt_border_l>0.0</amt_border_l>
				<amt_border_r>0.0</amt_border_r>
				<amt_border_kf>-1</amt_border_kf>
			</item>
			<item>
				<tx>-37.449133</tx>
				<ty>14.257563</ty>
				<tz>0.023133</tz>
				<rx>0.000000</rx>
				<ry>-0.000000</ry>
				<rz>0.000000</rz>
				<state>1</state>
				<occlusion>-1</occlusion>
				<occlusion_kf>-1</occlusion_kf>
				<truncation>-1</truncation>
				<amt_occlusion>0.0</amt_occlusion>
				<amt_occlusion_kf>-1</amt_occlusion_kf>
				<amt_border_l>0.0</amt_border_l>
				<amt_border_r>0.0</amt_border_r>
				<amt_border_kf>-1</amt_border_kf>
			</item>
			<item>
				<tx>-37.576348</tx>
				<ty>14.647156</ty>
				<tz>0.029819</tz>
				<rx>0.000000</rx>
				<ry>-0.000000</ry>
				<rz>0.000000</rz>
				<state>1</state>
				<occlusion>-1</occlusion>
				<occlusion_kf>-1</occlusion_kf>
				<truncation>-1</truncation>
				<amt_occlusion>0.0</amt_occlusion>
				<amt_occlusion_kf>-1</amt_occlusion_kf>
				<amt_border_l>0.0</amt_border_l>
				<amt_border_r>0.0</amt_border_r>
				<amt_border_kf>-1</amt_border_kf>
			</item>
			<item>
				<tx>-37.705224</tx>
				<ty>15.065204</ty>
				<tz>0.033182</tz>
				<rx>0.000000</rx>
				<ry>-0.000000</ry>
				<rz>0.000000</rz>
				<state>1</state>
				<occlusion>-1</occlusion>
				<occlusion_kf>-1</occlusion_kf>
				<truncation>-1</truncation>
				<amt_occlusion>0.0</amt_occlusion>
				<amt_occlusion_kf>-1</amt_occlusion_kf>
				<amt_border_l>0.0</amt_border_l>
				<amt_border_r>0.0</amt_border_r>
				<amt_border_kf>-1</amt_border_kf>
			</item>
			<item>
				<tx>-37.828281</tx>
				<ty>15.491098</ty>
				<tz>0.036504</tz>
				<rx>0.000000</rx>
				<ry>-0.000000</ry>
				<rz>0.000000</rz>
				<state>1</state>
				<occlusion>-1</occlusion>
				<occlusion_kf>-1</occlusion_kf>
				<truncation>-1</truncation>
				<amt_occlusion>0.0</amt_occlusion>
				<amt_occlusion_kf>-1</amt_occlusion_kf>
				<amt_border_l>0.0</amt_border_l>
				<amt_border_r>0.0</amt_border_r>
				<amt_border_kf>-1</amt_border_kf>
			</item>
			<item>
				<tx>-37.947300</tx>
				<ty>15.916493</ty>
				<tz>0.039601</tz>
				<rx>0.000000</rx>
				<ry>-0.000000</ry>
				<rz>0.000000</rz>
				<state>1</state>
				<occlusion>-1</occlusion>
				<occlusion_kf>-1</occlusion_kf>
				<truncation>-1</truncation>
				<amt_occlusion>0.0</amt_occlusion>
				<amt_occlusion_kf>-1</amt_occlusion_kf>
				<amt_border_l>0.0</amt_border_l>
				<amt_border_r>0.0</amt_border_r>
				<amt_border_kf>-1</amt_border_kf>
			</item>
			<item>
				<tx>-38.053974</tx>
				<ty>16.401405</ty>
				<tz>0.042708</tz>
				<rx>0.000000</rx>
				<ry>-0.000000</ry>
				<rz>0.000000</rz>
				<state>1</state>
				<occlusion>-1</occlusion>
				<occlusion_kf>-1</occlusion_kf>
				<truncation>-1</truncation>
				<amt_occlusion>0.0</amt_occlusion>
				<amt_occlusion_kf>-1</amt_occlusion_kf>
				<amt_border_l>0.0</amt_border_l>
				<amt_border_r>0.0</amt_border_r>
				<amt_border_kf>-1</amt_border_kf>
			</item>
			<item>
				<tx>-38.146018</tx>
				<ty>16.817972</ty>
				<tz>0.045347</tz>
				<rx>0.000000</rx>
				<ry>-0.000000</ry>
				<rz>0.000000</rz>
				<state>1</state>
				<occlusion>-1</occlusion>
				<occlusion_kf>-1</occlusion_kf>
				<truncation>-1</truncation>
				<amt_occlusion>0.0</amt_occlusion>
				<amt_occlusion_kf>-1</amt_occlusion_kf>
				<amt_border_l>0.0</amt_border_l>
				<amt_border_r>0.0</amt_border_r>
				<amt_border_kf>-1</amt_border_kf>
			</item>
			<item>
				<tx>-38.221315</tx>
				<ty>17.245897</ty>
				<tz>0.047640</tz>
				<rx>0.000000</rx>
				<ry>-0.000000</ry>
				<rz>0.000000</rz>
				<state>1</state>
				<occlusion>-1</occlusion>
				<occlusion_kf>-1</occlusion_kf>
				<truncation>-1</truncation>
				<amt_occlusion>0.0</amt_occlusion>
				<amt_occlusion_kf>-1</amt_occlusion_kf>
				<amt_border_l>0.0</amt_border_l>
				<amt_border_r>0.0</amt_border_r>
				<amt_border_kf>-1</amt_border_kf>
			</item>
			<item>
				<tx>-38.282803</tx>
				<ty>17.696353</ty>
				<tz>0.049932</tz>
				<rx>0.000000</rx>
				<ry>-0.000000</ry>
				<rz>0.000000</rz>
				<state>1</state>
				<occlusion>-1</occlusion>
				<occlusion_kf>-1</occlusion_kf>
				<truncation>-1</truncation>
				<amt_occlusion>0.0</amt_occlusion>
				<amt_occlusion_kf>-1</amt_occlusion_kf>
				<amt_border_l>0.0</amt_border_l>
				<amt_border_r>0.0</amt_border_r>
				<amt_border_kf>-1</amt_border_kf>
			</item>
			<item>
				<tx>-38.367480</tx>
				<ty>17.760822</ty>
				<tz>0.050900</tz>
				<rx>0.000000</rx>
				<ry>-0.000000</ry>
				<rz>0.000000</rz>
				<state>1</state>
				<occlusion>-1</occlusion>
				<occlusion_kf>-1</occlusion_kf>
				<truncation>-1</truncation>
				<amt_occlusion>0.0</amt_occlusion>
				<amt_occlusion_kf>-1</amt_occlusion_kf>
				<amt_border_l>0.0</amt_border_l>
				<amt_border_r>0.0</amt_border_r>
				<amt_border_kf>-1</amt_border_kf>
			</item>
		</poses>
		<finished>1</finished>
	</item>
</tracklets>
</boost_serialization> 
